[{"service_score": "6.7", "taste_score": "8.1", "img_url": "http://i2.s1.dpfile.com/pc/73849810a037029b90b32c2008b1cebb(249x249)/thumb.jpg", "name": "小龙记", "avg_cost": "0", "tags": "中餐", "review_score": "4", "address": "4853 Main St,Vancouver,", "atmosphere_score": "6.7", "review_num": "2"}
,{"service_score": "7.2", "taste_score": "7.6", "img_url": "http://i3.s1.dpfile.com/pc/73d80cd5f686005823d281f162642938(249x249)/thumb.jpg", "name": "QQ Bubble Tea & Coffee", "avg_cost": "0", "tags": "其他", "review_score": "4", "address": "8260 Westminster HWY,#2400号(近richmond center,公众市场2楼)", "atmosphere_score": "7.2", "review_num": "1"}
,{"service_score": "7.7", "taste_score": "7.7", "img_url": "http://i2.s1.dpfile.com/pc/7984d1bd7dedfdcede51b86e12ad0069(249x249)/thumb.jpg", "name": "Audrey s Moment", "avg_cost": "6.8", "tags": "其他", "review_score": "4", "address": "120B-6540 Burlington Ave,Burnaby", "atmosphere_score": "7.7", "review_num": "0"}
,{"service_score": "0", "phone": "604 685 0090", "taste_score": "0", "img_url": "http://i1.s1.dpfile.com/pc/cfdc054fcd245ea9ed3e1dd5f1e1f23e(249x249)/thumb.jpg", "name": "Secret Location", "avg_cost": "0", "review_score": "4.5", "address": "One Water Street, Vancouver, British Columbia V6B 2H9, Canada(Carrall Street)", "atmosphere_score": "0", "review_num": "0"}
,{"service_score": "0", "taste_score": "0", "img_url": "http://i1.s1.dpfile.com/pc/6a2f7c9d2e0f4f3015c9f84ba7ab012d(249x249)/thumb.jpg", "name": "Prospect Point Café", "avg_cost": "0", "review_score": "4", "address": "Stanley Park Dr", "atmosphere_score": "0", "review_num": "0"}
,{"service_score": "7.2", "taste_score": "7.5", "img_url": "http://i2.s1.dpfile.com/pc/d399db1cda9c378e926f62b604c112a6(249x249)/thumb.jpg", "name": "Suika", "avg_cost": "0", "review_score": "4", "address": "1626 W Broadway Vancouver", "atmosphere_score": "7.2", "review_num": "1"}
,{"service_score": "0", "phone": "+1 604 681 1164", "taste_score": "0", "img_url": "http://i2.s1.dpfile.com/pc/97e49854a3971e5c837bdec352372d98(249x249)/thumb.jpg", "name": "C Restaurant", "avg_cost": "0", "review_score": "4", "address": "1600 Howe St", "atmosphere_score": "0", "review_num": "0"}
,{"service_score": "7.5", "phone": "604-685-7502", "taste_score": "7.5", "img_url": "http://i3.s1.dpfile.com/pc/4f87f6880932f83b32144bd8799e621e(249x249)/thumb.jpg", "name": "The Keg Steakhouse & Bar", "avg_cost": "0", "review_score": "4", "address": "688 Dunsmuir Street | Downtown Vancouver, Vancouver, British Columbia V6B 1N3, Canada", "atmosphere_score": "7.5", "review_num": "2"}
,{"service_score": "0", "phone": "1-6331781", "taste_score": "0", "img_url": "http://i3.s1.dpfile.com/pc/84c0c068804bddce1c5c65f25ac110a0(249x249)/thumb.jpg", "name": "Templeton", "avg_cost": "0", "tags": "其他", "review_score": "4.5", "address": "1087 Granville St.", "atmosphere_score": "0", "review_num": "0"}
,{"service_score": "0", "phone": "1-9324540", "taste_score": "0", "img_url": "http://i3.s1.dpfile.com/pc/f082135d3e6bcf29d593b68553ae405d(249x249)/thumb.jpg", "name": "惠斯勒餐厅", "avg_cost": "0", "tags": "西餐", "review_score": "0", "address": "4222 Village Square, Whistler, BC V0N 1B4", "atmosphere_score": "0", "review_num": "0"}
,{"service_score": "0", "taste_score": "0", "img_url": "http://i2.s1.dpfile.com/pc/8b342487cbf472e5c2d668a59257bbfa(249x249)/thumb.jpg", "name": "Hogan's Alley Cafe", "avg_cost": "0", "review_score": "4", "address": "789 Gore St", "atmosphere_score": "0", "review_num": "0"}
,{"service_score": "0", "taste_score": "0", "img_url": "http://i3.s1.dpfile.com/pc/ddb7c364690a9e69f00d27447b27feb4(249x249)/thumb.jpg", "name": "Budgie's Burritos", "avg_cost": "0", "review_score": "4", "address": "44 Kingsway", "atmosphere_score": "0", "review_num": "0"}
,{"service_score": "0", "phone": "+1 604 299 2772", "taste_score": "0", "img_url": "http://i3.s1.dpfile.com/pc/491af34b7e58e6a537dead24b406729d(249x249)/thumb.jpg", "name": "Pear Tree", "avg_cost": "0", "review_score": "4", "address": "4120 E Hastings St, Burnaby", "atmosphere_score": "0", "review_num": "0"}
,{"service_score": "0", "taste_score": "0", "img_url": "http://i1.s1.dpfile.com/pc/61518fa1b9829fb07c37cf80d3287518(249x249)/thumb.jpg", "name": "El Camino's", "avg_cost": "0", "review_score": "4", "address": "3250 Main St", "atmosphere_score": "0", "review_num": "0"}
,{"service_score": "0", "phone": "+1 604 568 7022", "taste_score": "0", "img_url": "http://i1.s1.dpfile.com/pc/cce631034cf19e7be25b5320a14e444a(249x249)/thumb.jpg", "name": "Pourhouse", "avg_cost": "0", "review_score": "4", "address": "162 Water St", "atmosphere_score": "0", "review_num": "0"}
,{"service_score": "7.0", "phone": "1-6046818121", "taste_score": "7.4", "img_url": "http://i1.s1.dpfile.com/pc/c8414231bf19c3ffade82a250774132b(249x249)/thumb.jpg", "name": "Santouka Japanese Ramen", "avg_cost": "0", "tags": "其他", "review_score": "4", "address": "1690 Robson Street, Vancouver, BC, Canada", "atmosphere_score": "7.0", "review_num": "6"}
,{"service_score": "0", "taste_score": "0", "img_url": "http://i1.s1.dpfile.com/pc/90ccfb174ebec8e61eb7b11d2d6deb8a(249x249)/thumb.jpg", "name": "Crave", "avg_cost": "0", "review_score": "4", "address": "3941 Main St", "atmosphere_score": "0", "review_num": "0"}
,{"service_score": "0", "taste_score": "0", "img_url": "http://i3.s1.dpfile.com/pc/e317041315942d0ef6f49a8cc2561e11(249x249)/thumb.jpg", "name": "Timbre", "avg_cost": "0", "review_score": "4", "address": "2068 Commercial Dr", "atmosphere_score": "0", "review_num": "0"}
,{"service_score": "0", "taste_score": "0", "img_url": "http://i1.s1.dpfile.com/pc/2cb9517bcd85b89b32cf2304b9600488(249x249)/thumb.jpg", "name": "Naam", "avg_cost": "0", "review_score": "4", "address": "2724 W 4th Ave", "atmosphere_score": "0", "review_num": "0"}
,{"service_score": "0", "taste_score": "0", "img_url": "http://i2.s1.dpfile.com/pc/a2fa5640f34ee9303c3379d324fec5cd(249x249)/thumb.jpg", "name": "Artisan Bake Shoppe", "avg_cost": "0", "review_score": "4", "address": "127 Lonsdale Ave", "atmosphere_score": "0", "review_num": "0"}
,{"service_score": "0", "taste_score": "0", "img_url": "http://i2.s1.dpfile.com/pc/27f33f47fa3016703c794276582ec438(249x249)/thumb.jpg", "name": "Bob Likes Thai Food", "avg_cost": "0", "review_score": "4", "address": "3755 Main St", "atmosphere_score": "0", "review_num": "0"}
,{"service_score": "6.4", "taste_score": "6.8", "img_url": "http://i3.s1.dpfile.com/pc/8793c96152ebd9412c4aa6bce0e4cf70(249x249)/thumb.jpg", "name": "Terra Breads", "avg_cost": "0", "tags": "其他", "review_score": "3", "address": "107- 1689Johnston Street,Vancouver,BC V6H 3R9", "atmosphere_score": "6.4", "review_num": "1"}
,{"service_score": "0", "phone": "1-9263212", "taste_score": "0", "img_url": "http://i1.s1.dpfile.com/pc/5c5f8a7e383e3e4a8a3030c8f7174fb4(249x249)/thumb.jpg", "name": "鲑鱼屋", "avg_cost": "0", "tags": "其他", "review_score": "0", "address": "229 Folkestone Way, West Vancouver, BC, Canada", "atmosphere_score": "0", "review_num": "0"}
,{"service_score": "7.7", "taste_score": "7.7", "img_url": "http://i2.s1.dpfile.com/pc/ba1880ba3e38e85a26508dad60d5023f(249x249)/thumb.jpg", "name": "dinesty", "avg_cost": "0", "review_score": "4", "address": "robson St", "atmosphere_score": "7.7", "review_num": "2"}
,{"service_score": "7.0", "taste_score": "8.5", "img_url": "http://i3.s1.dpfile.com/pc/33dbcbd615b3c5366a4eeaf34367f58d(249x249)/thumb.jpg", "name": "Bella Gelateria And Gelato", "avg_cost": "0", "tags": "其他", "review_score": "4", "address": "1001 West Cordova Street,Vancouver,BC V6C0B7", "atmosphere_score": "7.0", "review_num": "3"}
,{"service_score": "6.8", "phone": "604-295-4072 ", "taste_score": "6.9", "img_url": "http://i2.s1.dpfile.com/pc/43881748e2f996457f1a4579e097d508(249x249)/thumb.jpg", "name": "Gyo-O 魚王", "avg_cost": "0", "tags": "日餐", "review_score": "3", "address": "3779 Sexsmith Rd, Richmond", "atmosphere_score": "6.8", "review_num": "3"}
,{"service_score": "7.5", "taste_score": "6.5", "img_url": "http://i2.s1.dpfile.com/pc/783898c350117486abe7a9735cba4f94(249x249)/thumb.jpg", "name": "Cactus Club Cafe", "avg_cost": "0", "tags": "西餐", "review_score": "3", "address": "588 Burrard St,Vancouver,BC", "atmosphere_score": "7.5", "review_num": "4"}
,{"service_score": "8.0", "phone": "604-370-3888", "taste_score": "8.2", "img_url": "http://i1.s1.dpfile.com/pc/469129cf2ad339fbec65fee6c63fc52d(249x249)/thumb.jpg", "name": "老西安", "avg_cost": "0", "tags": "其他", "review_score": "4", "address": "2010-8580 Alexandro Rd，Richmond", "atmosphere_score": "8.0", "review_num": "2"}
,{"service_score": "7.5", "phone": "604-279-0083", "taste_score": "7.6", "img_url": "http://i2.s1.dpfile.com/pc/2419939b3cd55075c72715187cc0f54e(249x249)/thumb.jpg", "name": "颐东其他酒楼", "avg_cost": "0", "tags": "其他", "review_score": "4", "address": "帝国中心，列治文", "atmosphere_score": "7.5", "review_num": "4"}
,{"service_score": "8.2", "phone": "+1 604-568-3900", "taste_score": "8.6", "img_url": "http://i1.s1.dpfile.com/pc/f16ec7f3b7d5f0b30f81bbe3091d6a72(249x249)/thumb.jpg", "name": "Miku", "avg_cost": "0", "review_score": "4", "address": "70-200 Granville St | Corner of Canada Way and Howe St, Vancouver, British Columbia V6C 2R6, Canada (Downtown)(Howe Street & Canada Place Way)", "atmosphere_score": "8.2", "review_num": "2"}
,{"service_score": "8.0", "taste_score": "7.6", "img_url": "http://i3.s1.dpfile.com/pc/b400207f72c0ff4ee5282907cc12e31c(249x249)/thumb.jpg", "name": "Thierry Chocolaterie Patisserie Cafe", "avg_cost": "0", "tags": "西餐", "review_score": "4", "address": "1059 Alberni Street, Vancouver", "atmosphere_score": "8.0", "review_num": "3"}
,{"service_score": "7.1", "phone": "1-8728050", "taste_score": "7.4", "img_url": "http://i3.s1.dpfile.com/pc/e0fddf125c8be62d02b3cd8c4dd4462f(249x249)/thumb.jpg", "name": "Tojo s寿司店", "avg_cost": "0", "tags": "日餐", "review_score": "4", "address": "202-777 West Broadway", "atmosphere_score": "7.1", "review_num": "1"}
,{"service_score": "8.4", "phone": "604-673-7000 ", "taste_score": "8.3", "img_url": "http://i1.s1.dpfile.com/pc/315c612bd0969fafe6cbb4335aa7239a(249x249)/thumb.jpg", "name": "Hawksworth Restaurant", "avg_cost": "0", "tags": "西餐", "review_score": "4", "address": "801 W Georgia St, Vancouver", "atmosphere_score": "8.4", "review_num": "2"}
,{"service_score": "8.1", "taste_score": "8.8", "img_url": "http://i1.s1.dpfile.com/pc/138caea218d396fa4716f33ff31a5114(249x249)/thumb.jpg", "name": "Cheesecake Etc", "avg_cost": "0", "tags": "甜点", "review_score": "4.5", "address": "2141 Granville St", "atmosphere_score": "8.1", "review_num": "5"}
,{"service_score": "6.8", "taste_score": "6.8", "img_url": "http://i1.s1.dpfile.com/pc/0735804d1773ddae32e1f04c095ae129(249x249)/thumb.jpg", "name": "Starbucks", "avg_cost": "0", "tags": "其他", "review_score": "3", "address": "818 West 6th Ave - False Creek", "atmosphere_score": "6.8", "review_num": "1"}
,{"service_score": "7.6", "taste_score": "7.9", "img_url": "http://i2.s1.dpfile.com/pc/e7667bf118775fe4d1d3751f70f80e7a(249x249)/thumb.jpg", "name": "Deer Garden Signatures", "avg_cost": "0", "tags": "其他", "review_score": "4", "address": "2015-8580 Alexandra Road Richmond, BC", "atmosphere_score": "7.6", "review_num": "5"}
,{"service_score": "6.8", "taste_score": "6.8", "img_url": "http://i2.s1.dpfile.com/pc/e08da1f1ed9cf17a4268b4b2c5120c44(249x249)/thumb.jpg", "name": "玉庭轩", "avg_cost": "0", "tags": "其他", "review_score": "3", "address": "8511 Alexandra Road,Richmond,BC V6X 1C3,Canada", "atmosphere_score": "6.8", "review_num": "1"}
,{"service_score": "6.9", "taste_score": "6.7", "img_url": "http://i3.s1.dpfile.com/pc/9f0760d15fd95266e32afb0db045ebaa(249x249)/thumb.jpg", "name": "Cobs Bread Bakery", "avg_cost": "0", "tags": "甜点", "review_score": "3", "address": "1160 Davie St,Vancouver,BC V6E 1N1加拿大", "atmosphere_score": "6.9", "review_num": "1"}
,{"service_score": "7.8", "phone": "1-6042791513", "taste_score": "7.9", "img_url": "http://i1.s1.dpfile.com/pc/28b2af2d8748e8997af9e75c890d3243(249x249)/thumb.jpg", "name": "名都其他酒家", "avg_cost": "0", "tags": "其他", "review_score": "4", "address": "110-8351 Alexandra Rd,Richmond, BC", "atmosphere_score": "7.8", "review_num": "5"}
,{"service_score": "7.3", "phone": "604-559-3990", "taste_score": "7.9", "img_url": "http://i1.s1.dpfile.com/pc/4fec10789a6995d999f39848e5cc0d14(249x249)/thumb.jpg", "name": "un's coffee", "avg_cost": "0", "tags": "西餐", "review_score": "4", "address": "1207 Hamilton Street, Vancouver(davie)", "atmosphere_score": "7.3", "review_num": "1"}
,{"service_score": "6.6", "phone": "1-4370828", "taste_score": "7.4", "img_url": "http://i2.s1.dpfile.com/pc/b90164da4988769b9bf6aca5bd520974(249x249)/thumb.jpg", "name": "湘緣湖南食府", "avg_cost": "0", "tags": "其他", "review_score": "4", "address": "4850 Imperial St, Burnaby, BC", "atmosphere_score": "6.6", "review_num": "5"}
,{"service_score": "7.2", "phone": "1-6883422", "taste_score": "7.5", "img_url": "http://i2.s1.dpfile.com/pc/592d762cf4708826a929e9790937c05c(249x249)/thumb.jpg", "name": "Caffe Artigiano", "avg_cost": "0", "tags": "其他", "review_score": "4", "address": "574 Granville St, Vancouver, BC V6C 1W6", "atmosphere_score": "7.2", "review_num": "1"}
,{"service_score": "6.9", "taste_score": "6.9", "img_url": "http://i2.s1.dpfile.com/pc/61ef39e0544beea21860807aad3ceae5(249x249)/thumb.jpg", "name": "IHOP", "avg_cost": "0", "tags": "快餐简餐", "review_score": "4", "address": "10551 St Edwards Street", "atmosphere_score": "6.9", "review_num": "1"}
,{"service_score": "7.5", "phone": "1-6042753753", "taste_score": "7.5", "img_url": "http://i1.s1.dpfile.com/pc/7b00bcbb664b48253cd8f6d03c7dd271(249x249)/thumb.jpg", "name": "Cimona Cafe", "avg_cost": "0", "tags": "西餐", "review_score": "4", "address": "3791 Bayview Street, Suite 210, Richmond,", "atmosphere_score": "7.5", "review_num": "1"}
,{"service_score": "7.1", "phone": "1-6692225", "taste_score": "6.8", "img_url": "http://i3.s1.dpfile.com/pc/e0c82e290414f387e9cd109fab8ec30f(249x249)/thumb.jpg", "name": "The Boathouse Restaurant", "avg_cost": "0", "tags": "其他", "review_score": "3", "address": "1795 Beach Ave, Vancouver, British Columbia, V6G 1Y9, Canada", "atmosphere_score": "7.1", "review_num": "1"}
,{"service_score": "7.2", "phone": "1-6042761180", "taste_score": "7.2", "img_url": "http://i2.s1.dpfile.com/pc/6a2ff0e11942540d15f16f240f871176(249x249)/thumb.jpg", "name": "Chop Steakhouse & Bar - Richmond", "avg_cost": "0", "tags": "其他", "review_score": "4", "address": "10251 St Edwards Dr, Richmond, BC V6X 2M9", "atmosphere_score": "7.2", "review_num": "1"}
,{"service_score": "6.9", "phone": "604-284-5596 ", "taste_score": "7.0", "img_url": "http://i1.s1.dpfile.com/pc/33e9b4ead3598908a9f2f3054f6e4b34(249x249)/thumb.jpg", "name": "Haroo Restaurant", "avg_cost": "0", "tags": "日餐", "review_score": "4", "address": "8580 Alexandra Rd, Richmond,", "atmosphere_score": "6.9", "review_num": "1"}
,{"service_score": "7.1", "taste_score": "7.3", "img_url": "http://i1.s1.dpfile.com/pc/fd1a8aabd15ff21592b1500e707f818f(249x249)/thumb.jpg", "name": "Empire Chinese Cuisine", "avg_cost": "0", "tags": "其他", "review_score": "4", "address": "8251 Alexandra Rd Richmond, BC", "atmosphere_score": "7.1", "review_num": "3"}
,{"service_score": "7.1", "phone": "604-370-4833", "taste_score": "7.1", "img_url": "http://i1.s1.dpfile.com/pc/d0f0142f72f28e4d769f96dd656a216c(249x249)/thumb.jpg", "name": "尚品其他面馆", "avg_cost": "0", "tags": "其他", "review_score": "4", "address": "1120-8391 Alexandra Rd Richmond BC V6X1C3", "atmosphere_score": "7.1", "review_num": "1"}
,{"service_score": "6.8", "taste_score": "7.1", "img_url": "http://i1.s1.dpfile.com/pc/469129cf2ad339fbec65fee6c63fc52d(249x249)/thumb.jpg", "name": "Chef Hung Taiwanese Beef Noodle", "avg_cost": "0", "tags": "其他", "review_score": "4", "address": "1560 Marine Drive West Vancouver BC ", "atmosphere_score": "6.8", "review_num": "1"}
,{"service_score": "0", "taste_score": "0", "img_url": "http://i1.s1.dpfile.com/pc/7b80d8250547fc42b32a5965b1068c91(249x249)/thumb.jpg", "name": "Havana", "avg_cost": "0", "review_score": "4", "address": "1212 Commercial Dr", "atmosphere_score": "0", "review_num": "0"}
,{"service_score": "0", "taste_score": "0", "img_url": "http://i2.s1.dpfile.com/pc/d412a04bbcc0ceb6891e4fed46b2af47(249x249)/thumb.jpg", "name": "Rumpus Room", "avg_cost": "0", "review_score": "4", "address": "2680 Main St", "atmosphere_score": "0", "review_num": "0"}
,{"service_score": "6.8", "phone": "604-278-6331", "taste_score": "7.4", "img_url": "http://i1.s1.dpfile.com/pc/9dd7ec44d00e94e960e0b8b57302f562(249x249)/thumb.jpg", "name": "幸运其他酒家", "avg_cost": "0", "tags": "其他", "review_score": "4", "address": "150-11700 Cambie Road, Road", "atmosphere_score": "6.8", "review_num": "1"}
,{"service_score": "0", "taste_score": "0", "img_url": "http://i1.s1.dpfile.com/pc/dfed7a3057c6d1d60d111c00ab451c24(249x249)/thumb.jpg", "name": "East is East", "avg_cost": "0", "review_score": "4", "address": "4413 Main St", "atmosphere_score": "0", "review_num": "0"}
,{"service_score": "6.7", "phone": "1-6044880399", "taste_score": "6.7", "img_url": "http://i2.s1.dpfile.com/pc/06e0ae8fd32af724914ba05f5841a47e(249x249)/thumb.jpg", "name": "New Peace Chinese Restaurant", "avg_cost": "0", "tags": "其他", "review_score": "3", "address": "630 Davie St.,Vancouver,British Columbia V6B 2G5,Canada", "atmosphere_score": "6.7", "review_num": "1"}
,{"service_score": "0", "taste_score": "0", "img_url": "http://i3.s1.dpfile.com/pc/47dffe2dcb8c51540d97eea715c10328(249x249)/thumb.jpg", "name": "Acme Cafe", "avg_cost": "0", "review_score": "4", "address": "51 W Hastings St", "atmosphere_score": "0", "review_num": "0"}
,{"service_score": "0", "phone": "+1 604 685 3924", "taste_score": "0", "img_url": "http://i3.s1.dpfile.com/pc/aa5c2f82c335de8f25ed965777c336dd(249x249)/thumb.jpg", "name": "Le Gavroche", "avg_cost": "0", "review_score": "4", "address": "1616 Alberni St", "atmosphere_score": "0", "review_num": "0"}
,{"service_score": "0", "taste_score": "0", "img_url": "http://i1.s1.dpfile.com/pc/fa1a72cd771d9f0dcf7feb310cf7730f(249x249)/thumb.jpg", "name": "Acorn", "avg_cost": "0", "review_score": "4", "address": "3995 Main St", "atmosphere_score": "0", "review_num": "0"}
,{"service_score": "0", "taste_score": "0", "img_url": "http://i2.s1.dpfile.com/pc/d412a04bbcc0ceb6891e4fed46b2af47(249x249)/thumb.jpg", "name": "Gene Cafe", "avg_cost": "0", "review_score": "4", "address": "2404 Main St", "atmosphere_score": "0", "review_num": "0"}
,{"service_score": "0", "phone": "+1 604 980 9311", "taste_score": "0", "img_url": "http://i1.s1.dpfile.com/pc/9ee187679c4b924b2272025b6131239a(249x249)/thumb.jpg", "name": "Observatory", "avg_cost": "0", "review_score": "4", "address": "Grouse Mountain", "atmosphere_score": "0", "review_num": "0"}
,{"service_score": "0", "taste_score": "0", "img_url": "http://i2.s1.dpfile.com/pc/3500a6c74322d710b74a190c8af6e21a(249x249)/thumb.jpg", "name": "Savary Island Pie Company", "avg_cost": "0", "review_score": "4", "address": "1533 Marine Dr", "atmosphere_score": "0", "review_num": "0"}
,{"service_score": "0", "taste_score": "0", "img_url": "http://i1.s1.dpfile.com/pc/c34c3050270222f48c3979d2313ac63e(249x249)/thumb.jpg", "name": "Agro Café", "avg_cost": "0", "review_score": "4", "address": "1363 Railspur Alley", "atmosphere_score": "0", "review_num": "0"}
,{"service_score": "0", "taste_score": "0", "img_url": "http://i3.s1.dpfile.com/pc/f20466a42bb7d78e8801977bbaa687b6(249x249)/thumb.jpg", "name": "Daily Grind Cafe", "avg_cost": "0", "review_score": "4", "address": "1500 W Georgia St", "atmosphere_score": "0", "review_num": "0"}
,{"service_score": "0", "phone": "+1 604 739 4677", "taste_score": "0", "img_url": "http://i2.s1.dpfile.com/pc/24a93804a53b174bbabf30b8160115d2(249x249)/thumb.jpg", "name": "Abigail's Party", "avg_cost": "0", "review_score": "4", "address": "1685 Yew St", "atmosphere_score": "0", "review_num": "0"}
,{"service_score": "0", "taste_score": "0", "img_url": "http://i3.s1.dpfile.com/pc/7676fb5c195e2254d8e664ffd7815ba1(249x249)/thumb.jpg", "name": "Nelson the Seagull", "avg_cost": "0", "review_score": "4", "address": "315 Carrall St", "atmosphere_score": "0", "review_num": "0"}
,{"service_score": "0", "taste_score": "0", "img_url": "http://i1.s1.dpfile.com/pc/4632db0b1c4aaa5dcb77b86d5ea50351(249x249)/thumb.jpg", "name": "Lolita's", "avg_cost": "0", "review_score": "4", "address": "1326 Davie St", "atmosphere_score": "0", "review_num": "0"}
,{"service_score": "0", "taste_score": "0", "img_url": "http://i1.s1.dpfile.com/pc/2cc7b8fb56b0f1c86c84e20fcb93b633(249x249)/thumb.jpg", "name": "Zakkushi", "avg_cost": "0", "review_score": "4", "address": "1833 W 4th Ave", "atmosphere_score": "0", "review_num": "0"}
,{"service_score": "0", "phone": "+1 604 732 0004", "taste_score": "0", "img_url": "http://i2.s1.dpfile.com/pc/bff902389ab96492fda21f6664ce3419(249x249)/thumb.jpg", "name": "La Cigale French Bistro", "avg_cost": "0", "review_score": "4", "address": "1961 W 4th Ave", "atmosphere_score": "0", "review_num": "0"}
,{"service_score": "0", "taste_score": "0", "img_url": "http://i3.s1.dpfile.com/pc/99b2149a7cfe78bf28aaa7a846c095bd(249x249)/thumb.jpg", "name": "Gorilla Food", "avg_cost": "0", "review_score": "4", "address": "436 Richards St", "atmosphere_score": "0", "review_num": "0"}
,{"service_score": "0", "taste_score": "0", "img_url": "http://i2.s1.dpfile.com/pc/315bc42ee27930535cdb8ef4eb963e58(249x249)/thumb.jpg", "name": "Carthage Cafe", "avg_cost": "0", "review_score": "4", "address": "1851 Commercial Dr", "atmosphere_score": "0", "review_num": "0"}
,{"service_score": "0", "taste_score": "0", "img_url": "http://i2.s1.dpfile.com/pc/b0c88db911e77cc3a38ff3f585cd4e34(249x249)/thumb.jpg", "name": "Uprising Breads Bakery Cafe", "avg_cost": "0", "review_score": "4", "address": "1697 Venables St", "atmosphere_score": "0", "review_num": "0"}
,{"service_score": "0", "phone": "+1 604 873 3131", "taste_score": "0", "img_url": "http://i2.s1.dpfile.com/pc/59b35e2f1186370893a3ffbc8f7af889(249x249)/thumb.jpg", "name": "Pied-a-Terre", "avg_cost": "0", "review_score": "4", "address": "3369 Cambia St", "atmosphere_score": "0", "review_num": "0"}
,{"service_score": "0", "taste_score": "0", "img_url": "http://i3.s1.dpfile.com/pc/e210e3d96b0fd912f04d7b7d3ae47ab6(249x249)/thumb.jpg", "name": "La Mezcaleria", "avg_cost": "0", "review_score": "4", "address": "1622 Commercial Dr", "atmosphere_score": "0", "review_num": "0"}
,{"service_score": "0", "phone": "1-6875288", "taste_score": "0", "img_url": "http://i2.s1.dpfile.com/pc/ffb12573d27891ad1807a953750702f2(249x249)/thumb.jpg", "name": "Capers", "avg_cost": "0", "tags": "其他", "review_score": "4", "address": "675 Robson St.", "atmosphere_score": "0", "review_num": "0"}
,{"service_score": "0", "taste_score": "0", "img_url": "http://i2.s1.dpfile.com/pc/a6250517428fbb819f811543b54c02e7(249x249)/thumb.jpg", "name": "La Taqueria Pinche Taco Shop", "avg_cost": "0", "review_score": "4", "address": "2549 Cambie St", "atmosphere_score": "0", "review_num": "0"}
,{"service_score": "0", "taste_score": "0", "img_url": "http://i3.s1.dpfile.com/pc/b5e2fb2ef27335aa1aa43f369741baf2(249x249)/thumb.jpg", "name": "Palki Restaurant", "avg_cost": "0", "review_score": "4", "address": "116 East 15th Street", "atmosphere_score": "0", "review_num": "0"}
,{"service_score": "0", "taste_score": "0", "img_url": "http://i1.s1.dpfile.com/pc/24743b4388738dc6290a422aca126869(249x249)/thumb.jpg", "name": "Cannibal Café", "avg_cost": "0", "review_score": "4", "address": "1818 Commercial Dr", "atmosphere_score": "0", "review_num": "0"}
,{"service_score": "0", "taste_score": "0", "img_url": "http://i2.s1.dpfile.com/pc/0c7ce080190e7966fb3c0d00975b6b91(249x249)/thumb.jpg", "name": "Rainier Provisions", "avg_cost": "0", "review_score": "4", "address": "2 W Cordova St", "atmosphere_score": "0", "review_num": "0"}
,{"service_score": "0", "taste_score": "0", "img_url": "http://i1.s1.dpfile.com/pc/8be5b7fd2ac12a5ef0711afd55e098d6(249x249)/thumb.jpg", "name": "Posh Charcoal Collaboration Dining", "avg_cost": "0", "review_score": "4", "address": "3779 Sexsmith Rd, Richmond", "atmosphere_score": "0", "review_num": "0"}
,{"service_score": "0", "taste_score": "0", "img_url": "http://i1.s1.dpfile.com/pc/8efa90589832e42eaec01bbcf7b2972d(249x249)/thumb.jpg", "name": "Deacon's Corner", "avg_cost": "0", "review_score": "4", "address": "101 Main St", "atmosphere_score": "0", "review_num": "0"}
,{"service_score": "0", "taste_score": "0", "img_url": "http://i3.s1.dpfile.com/pc/8a7be4ffc910eac69bbf96dde166dbba(249x249)/thumb.jpg", "name": "Sweet Cherubim", "avg_cost": "0", "review_score": "4", "address": "1105 Commercial Dr", "atmosphere_score": "0", "review_num": "0"}
,{"service_score": "0", "phone": "+1 604 730 5579", "taste_score": "0", "img_url": "http://i2.s1.dpfile.com/pc/dfdb66ec0a38ab64b84a5962dc3922cf(249x249)/thumb.jpg", "name": "Maenam", "avg_cost": "0", "review_score": "4", "address": "1938 W 4th Ave", "atmosphere_score": "0", "review_num": "0"}
,{"service_score": "0", "taste_score": "0", "img_url": "http://i2.s1.dpfile.com/pc/17802aa49452d4cb349f4c6de5933262(249x249)/thumb.jpg", "name": "Solly's Bagelry", "avg_cost": "0", "review_score": "4", "address": "268 W 7th Ave", "atmosphere_score": "0", "review_num": "0"}
,{"service_score": "0", "taste_score": "0", "img_url": "http://i2.s1.dpfile.com/pc/141b9fc63639298f4d66031ce0b22d32(249x249)/thumb.jpg", "name": "Aperture Coffee Bar", "avg_cost": "0", "review_score": "4", "address": "243 W Broadway", "atmosphere_score": "0", "review_num": "0"}
,{"service_score": "0", "taste_score": "0", "img_url": "http://i3.s1.dpfile.com/pc/9848b9bff538aa0afd6ecb173f46605c(249x249)/thumb.jpg", "name": "Tap & Barrel", "avg_cost": "0", "review_score": "4", "address": "1 Athletes Way", "atmosphere_score": "0", "review_num": "0"}
,{"service_score": "0", "taste_score": "0", "img_url": "http://i3.s1.dpfile.com/pc/56de839cc82d1a37b18f5283858d052a(249x249)/thumb.jpg", "name": "All India Sweets & Restaurant", "avg_cost": "0", "review_score": "4", "address": "6507 Main St", "atmosphere_score": "0", "review_num": "0"}
,{"service_score": "0", "phone": "1-7398185", "taste_score": "0", "img_url": "http://i1.s1.dpfile.com/pc/4a6141f2911c294ba40d3ccdc3edfcf2(249x249)/thumb.jpg", "name": "Lumiere", "avg_cost": "0", "tags": "其他", "review_score": "0", "address": "2551 West Broadway", "atmosphere_score": "0", "review_num": "0"}
,{"service_score": "0", "taste_score": "0", "img_url": "http://i3.s1.dpfile.com/pc/4a99a574acf377593952dbb543cae0d7(249x249)/thumb.jpg", "name": "Ouisi Bistro", "avg_cost": "0", "review_score": "4", "address": "3014 Granville St", "atmosphere_score": "0", "review_num": "0"}
,{"service_score": "0", "taste_score": "0", "img_url": "http://i3.s1.dpfile.com/pc/fd2a21bea82c7eabaeb7bdff43bea4da(249x249)/thumb.jpg", "name": "韩川豆腐锅", "avg_cost": "0", "tags": "其他", "review_score": "0", "address": "8328 Capstan Way RichmondBC V6X1R3", "atmosphere_score": "0", "review_num": "0"}
,{"service_score": "0", "taste_score": "0", "img_url": "http://i2.s1.dpfile.com/pc/bd93101d027f24a5391b20ef72bfe169(249x249)/thumb.jpg", "name": "TSUI HANG VILLAGE", "avg_cost": "0", "tags": "其他", "review_score": "0", "address": "1193 Granville Street,V6Z1L2,Vancouver BC,Canada", "atmosphere_score": "0", "review_num": "0"}
,{"service_score": "0", "phone": "604-4470888", "taste_score": "0", "img_url": "http://i2.s1.dpfile.com/pc/90bdf37b2d7ab4630dab0474bcc40a99(249x249)/thumb.jpg", "name": "火锅世家", "avg_cost": "0", "tags": "其他", "review_score": "0", "address": "3779 Sexsmith Road,Richmond", "atmosphere_score": "0", "review_num": "0"}
,{"service_score": "0", "taste_score": "0", "img_url": "http://i3.s1.dpfile.com/pc/72eb26fefc4fc80c9e613e8a6fe2ff8d(249x249)/thumb.jpg", "name": "Campagnolo", "avg_cost": "0", "review_score": "4", "address": "1020 Main St", "atmosphere_score": "0", "review_num": "0"}
,{"service_score": "0", "taste_score": "0", "img_url": "http://i1.s1.dpfile.com/pc/ad061edeb5d5e360101a6e4dfff030c7(249x249)/thumb.jpg", "name": "胖娃京川菜馆", "avg_cost": "0", "tags": "其他", "review_score": "0", "address": "8328 Capstan Way Richmond,BC V6X", "atmosphere_score": "0", "review_num": "0"}
,{"service_score": "0", "phone": "1-215252", "taste_score": "0", "img_url": "http://i3.s1.dpfile.com/pc/3fddb6e98ddd1fb0c7bf6f7727b4f12d(249x249)/thumb.jpg", "name": "Steveston Seafood House", "avg_cost": "0", "tags": "其他", "review_score": "0", "address": "3951 Moncton St, Richmond, BC", "atmosphere_score": "0", "review_num": "0"}
,{"service_score": "0", "taste_score": "0", "img_url": "http://i2.s1.dpfile.com/pc/ea8025994f6a92f2450f3e48d3b0e9aa(249x249)/thumb.jpg", "name": "重庆秦妈火锅", "avg_cost": "0", "tags": "其他", "review_score": "0", "address": "8080 Leslie Rd,Richmond,BC V6X 4A8", "atmosphere_score": "0", "review_num": "0"}
,{"service_score": "0", "taste_score": "0", "img_url": "http://i1.s1.dpfile.com/pc/9e8ffdcd4b1eb38b4d3f1105b1c90f2c(249x249)/thumb.jpg", "name": "Rain flower Restaurant", "avg_cost": "0", "tags": "其他", "review_score": "0", "address": "3600 No.3 Road, Richmond (Canadian Tire旁)", "atmosphere_score": "0", "review_num": "0"}
,{"service_score": "0", "taste_score": "0", "img_url": "http://i3.s1.dpfile.com/pc/75a40dfeb70e5145d6dcfa006625cb72(249x249)/thumb.jpg", "name": "白石海滨风景区北京饭店", "avg_cost": "0", "tags": "其他", "review_score": "0", "address": "15057 Marine Dr,White Rock,BC V4B 1C5", "atmosphere_score": "0", "review_num": "0"}
,{"service_score": "0", "taste_score": "0", "img_url": "http://i1.s1.dpfile.com/pc/d76f8b82c519ef96458091e0df081091(249x249)/thumb.jpg", "name": "味藏 Aji-Kura Ramen & Sushi", "avg_cost": "0", "tags": "其他", "review_score": "0", "address": "5857 Victoria Dr Vancouver,BC V5P3W5", "atmosphere_score": "0", "review_num": "0"}
,{"service_score": "0", "taste_score": "0", "img_url": "http://i1.s1.dpfile.com/pc/b82c4567046227f498a96f17a5b247ba(249x249)/thumb.jpg", "name": "香香妞川菜私房料理", "avg_cost": "0", "tags": "其他", "review_score": "0", "address": "8888 Odlin Cre,Richmond", "atmosphere_score": "0", "review_num": "0"}
,{"service_score": "0", "phone": "+1 604 682 4331", "taste_score": "0", "img_url": "http://i1.s1.dpfile.com/pc/0ac5459b9f7409093b47420962b76388(249x249)/thumb.jpg", "name": "No Frills", "avg_cost": "0", "review_score": "4", "address": "1030 Denman St", "atmosphere_score": "0", "review_num": "0"}
,{"service_score": "0", "taste_score": "0", "img_url": "http://i2.s1.dpfile.com/pc/25ccb05116f2364490fb2a3fbf2eea4b(249x249)/thumb.jpg", "name": "原烧Posh", "avg_cost": "0", "tags": "其他", "review_score": "0", "address": "6462 Kingsway Burnaby, BC V5E 1E1", "atmosphere_score": "0", "review_num": "0"}
,{"service_score": "6.7", "taste_score": "6.9", "img_url": "http://i3.s1.dpfile.com/pc/631d11bd76efbb5fc4cda8ed82b9897d(249x249)/thumb.jpg", "name": "北京小吃街", "avg_cost": "0", "tags": "中餐", "review_score": "3", "address": "列治文大统华超市二楼FoodCourt(时代坊北门马路对面)", "atmosphere_score": "6.7", "review_num": "2"}
,{"service_score": "8.1", "phone": "1-604568900", "taste_score": "7.7", "img_url": "http://i1.s1.dpfile.com/pc/2b745f1429805281541d76c04a7b07f1(249x249)/thumb.jpg", "name": "Miku Restaurant", "avg_cost": "0", "tags": "其他", "review_score": "4", "address": "Canada Pl, Vancouver, BC V6C", "atmosphere_score": "8.1", "review_num": "7"}
,{"service_score": "7.6", "phone": "604-428-9999", "taste_score": "7.5", "img_url": "http://i3.s1.dpfile.com/pc/7fc25b717360fe318fcffc673a94889e(249x249)/thumb.jpg", "name": "半岛公馆", "avg_cost": "0", "tags": "中餐", "review_score": "4", "address": "140 - 650 W. 41st Ave.Oakridge Centre", "atmosphere_score": "7.6", "review_num": "3"}
,{"service_score": "7.4", "taste_score": "7.4", "img_url": "http://i1.s1.dpfile.com/pc/4232fec29be8376451dc705f24b22ca2(249x249)/thumb.jpg", "name": "The KEG", "avg_cost": "0", "tags": "西餐", "review_score": "4", "address": "grandvill island", "atmosphere_score": "7.4", "review_num": "8"}
,{"service_score": "7.2", "phone": "604-685-2005", "taste_score": "7.9", "img_url": "http://i1.s1.dpfile.com/pc/1861bc40536878936480a03d195edcd4(249x249)/thumb.jpg", "name": "Rodney's Oyster House", "avg_cost": "0", "tags": "其他", "review_score": "4", "address": "1228 Hamilton Street,Vancouver,BC,Canada", "atmosphere_score": "7.2", "review_num": "7"}
,{"service_score": "8.2", "phone": "604-232-0816", "taste_score": "8.1", "img_url": "http://i2.s1.dpfile.com/pc/a9ab6a3c68882c2e03f7fbeafda5cbfa(249x249)/thumb.jpg", "name": "海港大酒楼", "avg_cost": "0", "tags": "中餐", "review_score": "4", "address": "8888 River Road, Richmond(River Rock)", "atmosphere_score": "8.2", "review_num": "4"}
,{"service_score": "7.5", "phone": "604-285-6122", "taste_score": "7.5", "img_url": "http://i1.s1.dpfile.com/pc/ebfddf609c0d7664ebc862d386771735(249x249)/thumb.jpg", "name": "重庆刘一手火锅", "avg_cost": "0", "tags": "其他", "review_score": "4", "address": "150-4731 Garden city Rd.Richmond BC", "atmosphere_score": "7.5", "review_num": "4"}
,{"service_score": "6.8", "phone": "1-6042787700", "taste_score": "7.3", "img_url": "http://i1.s1.dpfile.com/pc/522cfff1b7617cf224451ab5a044e02a(249x249)/thumb.jpg", "name": "九记", "avg_cost": "0", "tags": "快餐简餐", "review_score": "4", "address": "812-5300 Landowne Center No 3 Road", "atmosphere_score": "6.8", "review_num": "10"}
,{"service_score": "8.1", "phone": "1-6046781049", "taste_score": "8.0", "img_url": "http://i2.s1.dpfile.com/pc/008f049260a4c3ff7c01527cbd3a4460(249x249)/thumb.jpg", "name": "The Fish Shack", "avg_cost": "0", "tags": "其他", "review_score": "4", "address": "****1026, Granville St. Vancouver, BC", "atmosphere_score": "8.1", "review_num": "7"}
,{"service_score": "7.4", "phone": "604-278-8798", "taste_score": "8.1", "img_url": "http://i1.s1.dpfile.com/pc/0f6e5ff2724ecd3936e614b8b068f0bc(249x249)/thumb.jpg", "name": "上海一只鼎", "avg_cost": "0", "tags": "中餐", "review_score": "4", "address": "8100 Ackroyd Road, Richmond", "atmosphere_score": "7.4", "review_num": "14"}
,{"service_score": "6.9", "phone": "1-7319033", "taste_score": "7.0", "img_url": "http://i3.s1.dpfile.com/pc/285294720358f421ab4d5b0ee3d2a4de(249x249)/thumb.jpg", "name": "Denny's", "avg_cost": "42元", "tags": "快餐简餐", "review_score": "4", "address": "1296 Broadway West, Vancouver, BC V6H 1G6(近Staples)", "atmosphere_score": "6.9", "review_num": "12"}
,{"service_score": "8.0", "phone": "1-2738208", "taste_score": "8.3", "img_url": "http://i2.s1.dpfile.com/pc/72bbf706659ad433f9840140a8bb763e(249x249)/thumb.jpg", "name": "新瑞华其他酒家(Richmond总店)", "avg_cost": "0", "tags": "其他", "review_score": "4", "address": "加拿大温哥华#102-4940 No.3 Road", "atmosphere_score": "8.0", "review_num": "14"}
,{"service_score": "0", "phone": "604-687-6622", "taste_score": "0", "img_url": "http://i3.s1.dpfile.com/pc/1d9addf50f9c2e46d26953a21b27c1c8(249x249)/thumb.jpg", "name": "Shuraku Sake Bar & Bistro", "avg_cost": "0", "review_score": "4.5", "address": "833 Granville St., Vancouver, British Columbia, Canada (Downtown)(Robson Street)", "atmosphere_score": "0", "review_num": "0"}
,{"service_score": "8.0", "phone": "1-604-669-1940", "taste_score": "8.0", "img_url": "http://i3.s1.dpfile.com/pc/2b7a6c4b4a8b5e7d5c04eb9a60fcb5c1(249x249)/thumb.jpg", "name": "Joe Fortes Seafood & Chop House", "avg_cost": "0", "review_score": "4", "address": "777 Thurlow St,Vancouver,BC V6E 3V5加拿大", "atmosphere_score": "8.0", "review_num": "11"}
,{"service_score": "6.8", "taste_score": "8.2", "img_url": "http://i2.s1.dpfile.com/pc/083b5747b4b15b5f52f4da5d7759530d(249x249)/thumb.jpg", "name": "japadog", "avg_cost": "0", "tags": "其他", "review_score": "4", "address": "Burrard & Smithe ", "atmosphere_score": "6.8", "review_num": "6"}
,{"service_score": "0", "phone": "1-6044880045", "taste_score": "0", "img_url": "http://i2.s1.dpfile.com/pc/803eae6c1f08d64ed735e6001b5349d2(249x249)/thumb.jpg", "name": "Cafe Crepe", "avg_cost": "0", "review_score": "4.5", "address": "1032 Robson St, Vancouver, British Columbia V6E 1A7, Canada (Downtown)", "atmosphere_score": "0", "review_num": "0"}
,{"service_score": "0", "phone": "604.569.2535", "taste_score": "0", "img_url": "http://i2.s1.dpfile.com/pc/0e308c91ed6e4addf4c593cbccf726ff(249x249)/thumb.jpg", "name": "Lupo Restaurant", "avg_cost": "0", "review_score": "4.5", "address": "869 Hamilton St, Vancouver, British Columbia V6B 2R7, Canada(Between Robson & Smithe)", "atmosphere_score": "0", "review_num": "0"}
,{"service_score": "0", "taste_score": "0", "img_url": "http://i1.s1.dpfile.com/pc/3a5504cd5a249a7f40d3ab97c0462bca(249x249)/thumb.jpg", "name": "Mom's Grilled Cheese Truck", "avg_cost": "0", "review_score": "4.5", "address": "Corner of Howe Street & West Georgia | Vancouver Art Gallery Corner, Vancouver, British Columbia, Canada", "atmosphere_score": "0", "review_num": "0"}
,{"service_score": "0", "phone": "604.568.4554", "taste_score": "0", "img_url": "http://i3.s1.dpfile.com/pc/0619021969aa97a0144906898096e66d(249x249)/thumb.jpg", "name": "Nook", "avg_cost": "0", "review_score": "4.5", "address": "781 Denman Street, Vancouver, British Columbia V6G 2L6 , Canada (Downtown)", "atmosphere_score": "0", "review_num": "0"}
,{"service_score": "0", "phone": "604-633-3884", "taste_score": "0", "img_url": "http://i1.s1.dpfile.com/pc/b57184b264b0e11a43fbaf3fba457f40(249x249)/thumb.jpg", "name": "Acacia Fillo Bar", "avg_cost": "0", "review_score": "4.5", "address": "1103 Denman Street, Vancouver, British Columbia, Canada (Downtown)", "atmosphere_score": "0", "review_num": "0"}
,{"service_score": "0", "taste_score": "0", "img_url": "http://i3.s1.dpfile.com/pc/d89d4b9375bd1ecd8c967a483387d90b(249x249)/thumb.jpg", "name": "Guu with Garlic", "avg_cost": "0", "review_score": "4", "address": "1689 Robson St", "atmosphere_score": "0", "review_num": "0"}
,{"service_score": "0", "phone": "1-6046788488", "taste_score": "0", "img_url": "http://i3.s1.dpfile.com/pc/81bbd972062c4b07299da754bfe0c9e6(249x249)/thumb.jpg", "name": "Milestones", "avg_cost": "0", "review_score": "0", "address": "2425 Cambie StVancouver BC Canada", "atmosphere_score": "0", "review_num": "1"}
,{"service_score": "0", "phone": "(604) 875-6999", "taste_score": "0", "img_url": "http://i2.s1.dpfile.com/pc/68430a21dcdafbc97646ea73776c6d71(249x249)/thumb.jpg", "name": "U & I Thai Restaurant", "avg_cost": "0", "review_score": "4.5", "address": "3364 Cambie Street, Vancouver, British Columbia V5Z 2W5, Canada(between 17th and 18th Ave)", "atmosphere_score": "0", "review_num": "0"}
,{"service_score": "0", "phone": "1-6699030", "taste_score": "0", "img_url": "http://i1.s1.dpfile.com/pc/8887d3c4db821fb385e852e6fd5b7168(249x249)/thumb.jpg", "name": "The Sandbar Seafood Restaurant", "avg_cost": "0", "tags": "其他", "review_score": "4.5", "address": "1535 Johnston Street (Granville Island), Vancouver, British Columbia, V6H 3R9, Canada", "atmosphere_score": "0", "review_num": "0"}
,{"service_score": "0", "taste_score": "0", "img_url": "http://i1.s1.dpfile.com/pc/bc17bc64cbbb13172e299b7304cc90f1(249x249)/thumb.jpg", "name": "Tacofino Commissary", "avg_cost": "0", "review_score": "4.5", "address": "2327 East Hastings Street, Vancouver, British Columbia, Canada", "atmosphere_score": "0", "review_num": "0"}
,{"service_score": "6.7", "phone": "1-6042222233", "taste_score": "6.7", "img_url": "http://i3.s1.dpfile.com/pc/c4abd2030872e49ece6ec96ee7941053(249x249)/thumb.jpg", "name": "蓉城饭莊", "avg_cost": "0", "review_score": "3", "address": "4409 west 10th Avenue ,Vancouver Bc", "atmosphere_score": "6.7", "review_num": "1"}
,{"service_score": "0", "phone": "+1 604-568-1701", "taste_score": "0", "img_url": "http://i3.s1.dpfile.com/pc/1f0e75a9355163ac605c6a14029001f4(249x249)/thumb.jpg", "name": "L'Abattoir Restaurant", "avg_cost": "0", "review_score": "4.5", "address": "217 Carrall Street | GASTOWN, Vancouver, British Columbia V6B 2J2, Canada(Cordova Street)", "atmosphere_score": "0", "review_num": "0"}
,{"service_score": "0", "taste_score": "0", "img_url": "http://i3.s1.dpfile.com/pc/b69ba379f53fe2d0267d422d877c6b94(249x249)/thumb.jpg", "name": "Espana", "avg_cost": "0", "review_score": "4", "address": "1118 Denman St", "atmosphere_score": "0", "review_num": "0"}
,{"service_score": "0", "taste_score": "0", "img_url": "http://i3.s1.dpfile.com/pc/6ccd8771ef42c936c3e7fb3d3f6fcb55(249x249)/thumb.jpg", "name": "Judas Goat Taberna", "avg_cost": "0", "review_score": "4", "address": "27 Blood Alley", "atmosphere_score": "0", "review_num": "0"}
,{"service_score": "0", "phone": "+1 604-559-7968", "taste_score": "0", "img_url": "http://i1.s1.dpfile.com/pc/a814914cb75b623af6a991be5d33bb5c(249x249)/thumb.jpg", "name": "The Flying Pig", "avg_cost": "0", "review_score": "4.5", "address": "102 Water St, Vancouver, British Columbia V6B 1B2, Canada", "atmosphere_score": "0", "review_num": "0"}
,{"service_score": "0", "taste_score": "0", "img_url": "http://i3.s1.dpfile.com/pc/98e426a56d225f1353f5d4006c28137e(249x249)/thumb.jpg", "name": "Commune Cafe", "avg_cost": "0", "review_score": "4", "address": "1002 Seymour St", "atmosphere_score": "0", "review_num": "0"}
,{"service_score": "0", "taste_score": "0", "img_url": "http://i3.s1.dpfile.com/pc/1c341e0e55690dc7490b98d339062179(249x249)/thumb.jpg", "name": "Foundation", "avg_cost": "0", "review_score": "4", "address": "2301 Main St", "atmosphere_score": "0", "review_num": "0"}
,{"service_score": "0", "taste_score": "0", "img_url": "http://i3.s1.dpfile.com/pc/b91104b81bc054f36d39ff831df798f6(249x249)/thumb.jpg", "name": "Holy Trinity Ukrainian Orthodox Church", "avg_cost": "0", "review_score": "4", "address": "154 East 10th Ave", "atmosphere_score": "0", "review_num": "0"}
,{"service_score": "0", "taste_score": "0", "img_url": "http://i2.s1.dpfile.com/pc/8b2f06add335d67e037ef7463af5fdcf(249x249)/thumb.jpg", "name": "Heirloom Vegetarian", "avg_cost": "0", "review_score": "4", "address": "1509 W 12th Ave", "atmosphere_score": "0", "review_num": "0"}
,{"service_score": "0", "phone": "+1 604 488 0110", "taste_score": "0", "img_url": "http://i2.s1.dpfile.com/pc/5ef8729055b091a34914a165cb11b512(249x249)/thumb.jpg", "name": "Six Acres", "avg_cost": "0", "review_score": "4", "address": "203 Carrall St", "atmosphere_score": "0", "review_num": "0"}
,{"service_score": "0", "taste_score": "0", "img_url": "http://i3.s1.dpfile.com/pc/5fcde033d3e00efc12e849cc9604569e(249x249)/thumb.jpg", "name": "Burgoo Bistro", "avg_cost": "0", "review_score": "4", "address": "3 Lonsdale Ave", "atmosphere_score": "0", "review_num": "0"}
,{"service_score": "0", "taste_score": "0", "img_url": "http://i3.s1.dpfile.com/pc/8065d2b4017d5f5487a1328cfc2c46b2(249x249)/thumb.jpg", "name": "Sea Monstr Sushi", "avg_cost": "0", "review_score": "4", "address": "55 Powell St", "atmosphere_score": "0", "review_num": "0"}
,{"service_score": "0", "taste_score": "0", "img_url": "http://i3.s1.dpfile.com/pc/25b3260b0692dc9354bb3812b7fb902e(249x249)/thumb.jpg", "name": "Hawkers Delight", "avg_cost": "0", "review_score": "4", "address": "4127 Main St", "atmosphere_score": "0", "review_num": "0"}
,{"service_score": "0", "taste_score": "0", "img_url": "http://i2.s1.dpfile.com/pc/27868eb416c39c900bfb71213419c1b1(249x249)/thumb.jpg", "name": "Il Nido", "avg_cost": "0", "review_score": "4", "address": "780 Thurlow St", "atmosphere_score": "0", "review_num": "0"}
,{"service_score": "0", "phone": "+1 604 874 0922", "taste_score": "0", "img_url": "http://i2.s1.dpfile.com/pc/eaba8500b56fb483a5c42dd238553e5e(249x249)/thumb.jpg", "name": "Dutch Wooden Shoe Cafe", "avg_cost": "0", "review_score": "4", "address": "3292 Cambie St", "atmosphere_score": "0", "review_num": "0"}
,{"service_score": "0", "taste_score": "0", "img_url": "http://i3.s1.dpfile.com/pc/1a090a193245b9d6cbd91a59ee325f82(249x249)/thumb.jpg", "name": "Yopo Cafe", "avg_cost": "0", "review_score": "4", "address": "1122 Homer St", "atmosphere_score": "0", "review_num": "0"}
,{"service_score": "0", "taste_score": "0", "img_url": "http://i1.s1.dpfile.com/pc/69a4d146464b06a232c0e846e6935af3(249x249)/thumb.jpg", "name": "Café Calabria", "avg_cost": "0", "review_score": "4", "address": "1745 Commercial Dr", "atmosphere_score": "0", "review_num": "0"}
,{"service_score": "0", "phone": "+1 604 925 7595", "taste_score": "0", "img_url": "http://i2.s1.dpfile.com/pc/4c5e4c78429c80df89eabf7b47862809(249x249)/thumb.jpg", "name": "Fraîche", "avg_cost": "0", "review_score": "4", "address": "2240 Chippendale Rd", "atmosphere_score": "0", "review_num": "0"}
,{"service_score": "0", "taste_score": "0", "img_url": "http://i3.s1.dpfile.com/pc/956c0f47c183f92fae0fa11050ba063c(249x249)/thumb.jpg", "name": "Raglan's", "avg_cost": "0", "review_score": "4", "address": "15 Londsale Ave", "atmosphere_score": "0", "review_num": "0"}
,{"service_score": "0", "taste_score": "0", "img_url": "http://i3.s1.dpfile.com/pc/a29a73dd4c72318c7896039ae686ed32(249x249)/thumb.jpg", "name": "Moderne Burger", "avg_cost": "0", "review_score": "4", "address": "2507 W Broadway", "atmosphere_score": "0", "review_num": "0"}
,{"service_score": "0", "taste_score": "0", "img_url": "http://i1.s1.dpfile.com/pc/211bd91b6d34264e72da64ac6d50057b(249x249)/thumb.jpg", "name": "Wildebeest", "avg_cost": "0", "review_score": "4", "address": "120 W Hastings St", "atmosphere_score": "0", "review_num": "0"}
,{"service_score": "0", "taste_score": "0", "img_url": "http://i1.s1.dpfile.com/pc/73fb16e929b916dee0635f960d4454eb(249x249)/thumb.jpg", "name": "Noodle Box", "avg_cost": "0", "review_score": "4", "address": "1867 W 4th Ave", "atmosphere_score": "0", "review_num": "0"}
,{"service_score": "0", "taste_score": "0", "img_url": "http://i2.s1.dpfile.com/pc/18faf553e34e11e4941a28a54336fd1c(249x249)/thumb.jpg", "name": "Sushi Mart", "avg_cost": "0", "review_score": "4", "address": "1686 Robson St", "atmosphere_score": "0", "review_num": "0"}
,{"service_score": "0", "taste_score": "0", "img_url": "http://i1.s1.dpfile.com/pc/e09de1168f277c9f7b98b1f7bfc75166(249x249)/thumb.jpg", "name": "Belgian Fries", "avg_cost": "0", "review_score": "4", "address": "1185 Commercial Dr", "atmosphere_score": "0", "review_num": "0"}
,{"service_score": "0", "taste_score": "0", "img_url": "http://i2.s1.dpfile.com/pc/274dd4f1836c7816a2cf278c298e08fb(249x249)/thumb.jpg", "name": "Stanley's Park Bar & Grill", "avg_cost": "0", "review_score": "4", "address": "610 Pipeline Rd", "atmosphere_score": "0", "review_num": "0"}
,{"service_score": "0", "taste_score": "0", "img_url": "http://i3.s1.dpfile.com/pc/971f0e47a0571a11518bdcc488a23c94(249x249)/thumb.jpg", "name": "Public Market Food Court", "avg_cost": "0", "review_score": "4", "address": "1661 Duranleau St", "atmosphere_score": "0", "review_num": "0"}
,{"service_score": "0", "taste_score": "0", "img_url": "http://i3.s1.dpfile.com/pc/cb6c7a7df89bf9d51887c203f8dd3f6c(249x249)/thumb.jpg", "name": "Reef", "avg_cost": "0", "review_score": "4", "address": "1018 Commercial Dr", "atmosphere_score": "0", "review_num": "0"}
,{"service_score": "0", "taste_score": "0", "img_url": "http://i2.s1.dpfile.com/pc/dac05a3ead234e7bcea72a788d178dee(249x249)/thumb.jpg", "name": "Burgoo Bistro", "avg_cost": "0", "review_score": "4", "address": "3096 Main St", "atmosphere_score": "0", "review_num": "0"}
,{"service_score": "0", "taste_score": "0", "img_url": "http://i3.s1.dpfile.com/pc/da780b466754d73690401ef562783d7d(249x249)/thumb.jpg", "name": "Beaucoup Bakery & Cafe", "avg_cost": "0", "review_score": "4", "address": "2150 Fir St", "atmosphere_score": "0", "review_num": "0"}
,{"service_score": "0", "phone": "+1 604 684 1844", "taste_score": "0", "img_url": "http://i3.s1.dpfile.com/pc/cbc26e4bc4044ee28c4c49c6076016f9(249x249)/thumb.jpg", "name": "Boneta", "avg_cost": "0", "review_score": "4", "address": "12 Water St", "atmosphere_score": "0", "review_num": "0"}
,{"service_score": "7.5", "phone": "1-2706169", "taste_score": "7.5", "img_url": "http://j3.s2.dpfile.com/s/c/app/shop/i/shop/no-photo-v2.cb489b6dc9f2efe05219ddb61bde98a8.png", "name": "老四川", "avg_cost": "0", "review_score": "4", "address": "No. 3631 No.3 Rd, Richmond (近八佰伴)", "atmosphere_score": "7.5", "review_num": "2"}
,{"service_score": "8.2", "phone": "604-278-0873", "taste_score": "8.3", "img_url": "http://i1.s1.dpfile.com/pc/e7d3a4c986971d4e9711f710b1516813(249x249)/thumb.jpg", "name": "金百乐其他酒家", "avg_cost": "0", "tags": "其他", "review_score": "4", "address": "8071 Park Rd", "atmosphere_score": "8.2", "review_num": "2"}
,{"service_score": "6.9", "taste_score": "7.4", "img_url": "http://i2.s1.dpfile.com/pc/2ece341111e3f9d351683c9e5356ffa0(249x249)/thumb.jpg", "name": "赵记汤馆", "avg_cost": "0", "tags": "中餐", "review_score": "3", "address": "8511 Alexandra road,Richmond", "atmosphere_score": "6.9", "review_num": "2"}
,{"service_score": "8.4", "phone": "604-605-8282", "taste_score": "8.4", "img_url": "http://i1.s1.dpfile.com/pc/fc2f6298a573e94c96a356147ee1ca63(249x249)/thumb.jpg", "name": "Gotham", "avg_cost": "0", "tags": "西餐", "review_score": "4", "address": "615 seymour street, Vancouver", "atmosphere_score": "8.4", "review_num": "2"}
,{"service_score": "6.8", "taste_score": "7.1", "img_url": "http://i2.s1.dpfile.com/pc/b2636764d551024a1919a3df20bb1219(249x249)/thumb.jpg", "name": "王记-台湾牛肉面", "avg_cost": "0", "tags": "快餐简餐", "review_score": "4", "address": "8450 Granville St Vancouver, BC V6P", "atmosphere_score": "6.8", "review_num": "1"}
,{"service_score": "6.8", "taste_score": "7.1", "img_url": "http://i1.s1.dpfile.com/pc/950c1184713ebf3524867a8870c66ae5(249x249)/thumb.jpg", "name": "嫁‘Ge'冷 潮州菜", "avg_cost": "0", "tags": "其他", "review_score": "4", "address": "2150-8391号alexandra road richmondbc v6x 3w5", "atmosphere_score": "6.8", "review_num": "1"}
,{"service_score": "7.0", "taste_score": "7.5", "img_url": "http://i1.s1.dpfile.com/pc/6fe8465a9389ab28ccf3364da7b4c48a(249x249)/thumb.jpg", "name": "串香居烧烤", "avg_cost": "0", "tags": "其他", "review_score": "4", "address": "3399 Kingsway,Vancouver BC CanadaV5R 5K6", "atmosphere_score": "7.0", "review_num": "2"}
,{"service_score": "7.1", "phone": "1-6042944100", "taste_score": "7.4", "img_url": "http://i1.s1.dpfile.com/pc/0ff0439b6dd0c75e7036502d2121010e(249x249)/thumb.jpg", "name": "樱茶屋 Blossom Teas", "avg_cost": "0", "tags": "西餐", "review_score": "4", "address": "23-7198 Barnet Road, Burnaby(SFU西门菲莎大学)", "atmosphere_score": "7.1", "review_num": "1"}
,{"service_score": "8.1", "phone": "1-9157200", "taste_score": "8.3", "img_url": "http://i1.s1.dpfile.com/pc/6168b07e216523903c8253858ebccb6b(249x249)/thumb.jpg", "name": "Caffe Artigiano", "avg_cost": "0", "tags": "其他", "review_score": "4", "address": "740 W Hastings St, Vancouver, BC V6B 1N9", "atmosphere_score": "8.1", "review_num": "3"}
,{"service_score": "7.1", "taste_score": "7.1", "img_url": "http://i3.s1.dpfile.com/pc/1a3e79206e5d8e3b757b21db27e98399(249x249)/thumb.jpg", "name": "Pho Khang Vietnamese Restaurant", "avg_cost": "0", "tags": "中餐", "review_score": "4", "address": "206 - 6551 No.3 Road, Richmond, BC, Canada.(列治文三号路夹威廉姆斯路口，加油站南走50米，KFC隔壁)", "atmosphere_score": "7.1", "review_num": "1"}
,{"service_score": "7.3", "phone": "1-6081677", "taste_score": "8.2", "img_url": "http://i1.s1.dpfile.com/pc/88a293dde85c1ac6ad70208d8254827b(249x249)/thumb.jpg", "name": "Kingyo", "avg_cost": "0", "tags": "其他", "review_score": "4", "address": "871 Denman Street, Vancouver, British Columbia, Canada", "atmosphere_score": "7.3", "review_num": "2"}
,{"service_score": "8.5", "phone": "604-669-3281", "taste_score": "7.5", "img_url": "http://i3.s1.dpfile.com/pc/3fb7b043946245eb5fbe2212ce1f50a8(249x249)/thumb.jpg", "name": "Teahouse in Stanley Park", "avg_cost": "0", "review_score": "4", "address": "7501 Stanley Park Drive, Vancouver, British Columbia V6G3E2, Canada(Third Beach)", "atmosphere_score": "8.5", "review_num": "2"}
,{"service_score": "6.8", "phone": "1-6046887338", "taste_score": "6.6", "img_url": "http://i3.s1.dpfile.com/pc/5f0f8268f7f5b37c0742346dd30a84f0(249x249)/thumb.jpg", "name": "Cin Cin Ristorante + Bar", "avg_cost": "0", "tags": "西餐", "review_score": "3", "address": "1154 Robson St, Vancouver, British Columbia V6E 1B2, Canada", "atmosphere_score": "6.8", "review_num": "4"}
,{"service_score": "6.8", "phone": "1-6887788", "taste_score": "7.1", "img_url": "http://i2.s1.dpfile.com/pc/baea57013a38f03de74fde095cf04626(249x249)/thumb.jpg", "name": "北京饭店", "avg_cost": "0", "tags": "其他", "review_score": "3", "address": "865 Hornby Street", "atmosphere_score": "6.8", "review_num": "1"}
,{"service_score": "0", "phone": "+1 604 255 8926", "taste_score": "0", "img_url": "http://i1.s1.dpfile.com/pc/7a384fda6930135343b02c82549bf943(249x249)/thumb.jpg", "name": "Fratelli Baking", "avg_cost": "0", "review_score": "4", "address": "1795 Commercial Dr", "atmosphere_score": "0", "review_num": "0"}
,{"service_score": "6.5", "phone": "604-6888-078", "taste_score": "7.1", "img_url": "http://i1.s1.dpfile.com/pc/a79695c335f72dfe55fb2461583c4e11(249x249)/thumb.jpg", "name": "Blue Water Cafe + Raw Bar", "avg_cost": "0", "tags": "西餐", "review_score": "3", "address": "1095 Hamilton St,Vancouver,BC V6B 5T4加拿大", "atmosphere_score": "6.5", "review_num": "1"}
,{"service_score": "8.4", "taste_score": "8.4", "img_url": "http://i3.s1.dpfile.com/pc/6c44e3ddcc554e2a1c2a794f660e0e59(249x249)/thumb.jpg", "name": "Gallery Café", "avg_cost": "0", "review_score": "4", "address": "750 Hornby St", "atmosphere_score": "8.4", "review_num": "1"}
,{"service_score": "8.4", "taste_score": "8.4", "img_url": "http://i3.s1.dpfile.com/pc/037fc65979a3915748e980612c4a67e4(249x249)/thumb.jpg", "name": "Thomas Haas Patisserie", "avg_cost": "0", "tags": "西餐", "review_score": "4", "address": "128-998 Harbourside Drive, North Vancouver", "atmosphere_score": "8.4", "review_num": "1"}
,{"service_score": "7.9", "phone": "1-6046692220", "taste_score": "7.4", "img_url": "http://i2.s1.dpfile.com/pc/d8e2d8af560b5008a23e9e541e341b4e(249x249)/thumb.jpg", "name": "Top of Vancouver", "avg_cost": "0", "tags": "西餐", "review_score": "4", "address": "555 west hastings street,vancouver,canada", "atmosphere_score": "7.9", "review_num": "2"}
,{"service_score": "7.5", "taste_score": "8.0", "img_url": "http://i3.s1.dpfile.com/pc/2ff145ff4c5102b174dd63745bcced95(249x249)/thumb.jpg", "name": "tepho's", "avg_cost": "0", "review_score": "4", "address": "1359 Robson Street，Vancouver，BC", "atmosphere_score": "7.5", "review_num": "2"}
,{"service_score": "6.8", "phone": "1-6042580005", "taste_score": "7.1", "img_url": "http://i3.s1.dpfile.com/pc/ec62d28a7402441b927eb1bc34f0de8b(249x249)/thumb.jpg", "name": "Merchant's oyster bar", "avg_cost": "0", "tags": "西餐", "review_score": "4", "address": "1590 commercial Drive", "atmosphere_score": "6.8", "review_num": "1"}
,{"service_score": "8.4", "phone": "604-692-4939", "taste_score": "8.4", "img_url": "http://i2.s1.dpfile.com/pc/876fb9f84b2cf979619eb20c5e663b42(249x249)/thumb.jpg", "name": "Yew Seafood + Bar", "avg_cost": "0", "review_score": "4", "address": "Four Seasons Hotel Vancouver | 791 West Georgia Street, Vancouver, British Columbia V6C 2T4, Canada (Formerly Yew Restaurant + Bar)(Downtown)(Howe & West Georgia)", "atmosphere_score": "8.4", "review_num": "1"}
,{"service_score": "7.4", "taste_score": "7.4", "img_url": "http://i1.s1.dpfile.com/pc/554a6c973845a3a84f002a8e43b16940(249x249)/thumb.jpg", "name": "Kim House Japanese Bis", "avg_cost": "0", "tags": "中餐", "review_score": "4", "address": "538 SEYMOUR ST.VANCOUVER,CANADA", "atmosphere_score": "7.4", "review_num": "2"}
,{"service_score": "6.9", "phone": "1-6046819321", "taste_score": "6.9", "img_url": "http://i2.s1.dpfile.com/pc/8668dd5b0954dae60aa8375a2802ac4c(249x249)/thumb.jpg", "name": "Sylvia's Restaurant", "avg_cost": "0", "review_score": "4", "address": "1154 Gilford St, Vancouver, British Columbia, Canada", "atmosphere_score": "6.9", "review_num": "1"}
,{"service_score": "8.4", "phone": "1-6694298", "taste_score": "8.4", "img_url": "http://i1.s1.dpfile.com/pc/84d043830bb1dfea5328ae30fe3bae22(249x249)/thumb.jpg", "name": "Le Crocodile Restaurant", "avg_cost": "0", "tags": "其他", "review_score": "4", "address": "909 Burrard Street #100, Vancouver, BC, Canada", "atmosphere_score": "8.4", "review_num": "1"}
,{"service_score": "6.9", "phone": "604-214-1402 ", "taste_score": "7.0", "img_url": "http://i2.s1.dpfile.com/pc/59bb72c599fe4252ad2651f4cab22b03(249x249)/thumb.jpg", "name": "虎连坊", "avg_cost": "0", "tags": "日餐", "review_score": "4", "address": "8191 Park Rd, Richmond", "atmosphere_score": "6.9", "review_num": "1"}
,{"service_score": "0", "taste_score": "0", "img_url": "http://i1.s1.dpfile.com/pc/8b96683ee460a1c13292ede9a110ba35(249x249)/thumb.jpg", "name": "Sun Sui Wah Seafood Restaurant", "avg_cost": "0", "review_score": "4", "address": "3888 Main St", "atmosphere_score": "0", "review_num": "0"}
,{"service_score": "0", "taste_score": "0", "img_url": "http://i3.s1.dpfile.com/pc/2ac3c73801525f98e488add795b2bf1f(249x249)/thumb.jpg", "name": "Hon's Wun-Tun House", "avg_cost": "0", "review_score": "4", "address": "268 E Keefer St", "atmosphere_score": "0", "review_num": "0"}
,{"service_score": "6.9", "taste_score": "6.9", "img_url": "http://i1.s1.dpfile.com/pc/f331dd5ecf034ac5c1f0fad3ebfab241(249x249)/thumb.jpg", "name": "Pho Queen Restaurant", "avg_cost": "0", "tags": "中餐", "review_score": "3", "address": "列治文新城市广场（Capstan Way 靠近 No.3 Road）(八佰伴和Canadian Tire东侧 )", "atmosphere_score": "6.9", "review_num": "1"}
,{"service_score": "0", "taste_score": "0", "img_url": "http://i2.s1.dpfile.com/pc/47b4291eda2b1e6cd9c67c496ee27e0e(249x249)/thumb.jpg", "name": "French Made Baking", "avg_cost": "0", "review_score": "4", "address": "81 Kingsway", "atmosphere_score": "0", "review_num": "0"}
,{"service_score": "0", "phone": "+1 604 602 0835", "taste_score": "0", "img_url": "http://i3.s1.dpfile.com/pc/e5a43e25afb1020f776864e8480b56e9(249x249)/thumb.jpg", "name": "Glowbal Grill Steak & Satay", "avg_cost": "0", "review_score": "4", "address": "1079 Mainland St", "atmosphere_score": "0", "review_num": "0"}
,{"service_score": "7.0", "phone": "778-297-9998", "taste_score": "7.0", "img_url": "http://i2.s1.dpfile.com/pc/04b62fcfc88344cf40a25edff5e2682a(249x249)/thumb.jpg", "name": "上海金典", "avg_cost": "0", "tags": "其他", "review_score": "3", "address": "2170-8788 Mckim Way, Richmond", "atmosphere_score": "7.0", "review_num": "2"}
,{"service_score": "0", "taste_score": "0", "img_url": "http://i3.s1.dpfile.com/pc/df2264df2901c7d4dfbd047c57bacca2(249x249)/thumb.jpg", "name": "Rangoli", "avg_cost": "0", "review_score": "4", "address": "1488 W 11th Ave", "atmosphere_score": "0", "review_num": "0"}
,{"service_score": "0", "taste_score": "0", "img_url": "http://i1.s1.dpfile.com/pc/3468d78b17a51c69347b2a85bcf7f40c(249x249)/thumb.jpg", "name": "Tomahawk Restaurant", "avg_cost": "0", "review_score": "4", "address": "1550 Philip Ave", "atmosphere_score": "0", "review_num": "0"}
,{"service_score": "0", "taste_score": "0", "img_url": "http://i1.s1.dpfile.com/pc/31e9c1a74d3a59d10a69d6f0e5880f1f(249x249)/thumb.jpg", "name": "Argo Cafe", "avg_cost": "0", "review_score": "4", "address": "1836 Ontario St", "atmosphere_score": "0", "review_num": "0"}
,{"service_score": "0", "taste_score": "0", "img_url": "http://i3.s1.dpfile.com/pc/f0bb15990c24ae9e6e8006c6300ab5ec(249x249)/thumb.jpg", "name": "Paul's Omelettery", "avg_cost": "0", "review_score": "4", "address": "2211 Granville St", "atmosphere_score": "0", "review_num": "0"}
,{"service_score": "8.4", "phone": "1-6045682998", "taste_score": "8.4", "img_url": "http://i1.s1.dpfile.com/pc/9b0e12770e7cab8a3ee37dde5f3a6abf(249x249)/thumb.jpg", "name": "VANVAN JANPANSES TAPAS IZAKAYA", "avg_cost": "0", "tags": "其他", "review_score": "4.5", "address": "1333 ROBSON ST. VANCOUVER BC V6E 1C6(Robson购物街中心位置，靠近太平洋中心)", "atmosphere_score": "8.4", "review_num": "2"}
,{"service_score": "0", "taste_score": "0", "img_url": "http://i3.s1.dpfile.com/pc/0ff0f1b5b5acc204c684503b53b72d72(249x249)/thumb.jpg", "name": "Chutney Villa", "avg_cost": "0", "review_score": "4", "address": "147 E Broadway", "atmosphere_score": "0", "review_num": "0"}
,{"service_score": "0", "phone": "+1 604 685 7337", "taste_score": "0", "img_url": "http://i2.s1.dpfile.com/pc/2c25479f14971eba15568673fa5930f1(249x249)/thumb.jpg", "name": "Raincity Grill", "avg_cost": "0", "review_score": "4", "address": "1193 Denman St", "atmosphere_score": "0", "review_num": "0"}
,{"service_score": "0", "taste_score": "0", "img_url": "http://i2.s1.dpfile.com/pc/99fa050bf97ae7801147dd96e9d47367(249x249)/thumb.jpg", "name": "Save On Meats", "avg_cost": "0", "review_score": "4", "address": "43 W Hastings St", "atmosphere_score": "0", "review_num": "0"}
,{"service_score": "0", "taste_score": "0", "img_url": "http://i1.s1.dpfile.com/pc/f8e0b0eb35465a7ded9679616d7110b6(249x249)/thumb.jpg", "name": "Motomachi Shokudo", "avg_cost": "0", "review_score": "4", "address": "740 Denman St", "atmosphere_score": "0", "review_num": "0"}
,{"service_score": "0", "taste_score": "0", "img_url": "http://i2.s1.dpfile.com/pc/e4a9eb71d741f28505097aa42c26b032(249x249)/thumb.jpg", "name": "Toshi Sushi", "avg_cost": "0", "review_score": "4", "address": "181 E 16th Ave", "atmosphere_score": "0", "review_num": "0"}
,{"service_score": "0", "taste_score": "0", "img_url": "http://i2.s1.dpfile.com/pc/11e4cf87819ce1cfdc590b00b08194b0(249x249)/thumb.jpg", "name": "Prophouse Cafe", "avg_cost": "0", "review_score": "4", "address": "1636 Venables St", "atmosphere_score": "0", "review_num": "0"}
,{"service_score": "0", "taste_score": "0", "img_url": "http://i3.s1.dpfile.com/pc/3300df3aeb6d7bde53aee7af304aa046(249x249)/thumb.jpg", "name": "Benton Brothers Fine Cheese", "avg_cost": "0", "review_score": "4", "address": "3423 Cambie St", "atmosphere_score": "0", "review_num": "0"}
,{"service_score": "0", "taste_score": "0", "img_url": "http://i1.s1.dpfile.com/pc/86d3880c896263acafe9f1b0434f456a(249x249)/thumb.jpg", "name": "La Casa Gelato", "avg_cost": "0", "review_score": "4", "address": "1033 Venables St", "atmosphere_score": "0", "review_num": "0"}
,{"service_score": "0", "taste_score": "0", "img_url": "http://i3.s1.dpfile.com/pc/2fc51872e700aecc49656dae029b4fc0(249x249)/thumb.jpg", "name": "Falconetti's East Side Grill", "avg_cost": "0", "review_score": "4", "address": "1812 Commercial Dr", "atmosphere_score": "0", "review_num": "0"}
,{"service_score": "0", "taste_score": "0", "img_url": "http://i1.s1.dpfile.com/pc/5fd30cc5d25fc89790e95f7e82b271b0(249x249)/thumb.jpg", "name": "Cartems Donuterie", "avg_cost": "0", "review_score": "4", "address": "408 Carrall St", "atmosphere_score": "0", "review_num": "0"}
,{"service_score": "0", "taste_score": "0", "img_url": "http://i3.s1.dpfile.com/pc/dde9a7cb7a307edea49e33ecce7c76ad(249x249)/thumb.jpg", "name": "Provence Marinaside", "avg_cost": "0", "review_score": "4", "address": "1177 Marinaside Crescent", "atmosphere_score": "0", "review_num": "0"}
,{"service_score": "0", "taste_score": "0", "img_url": "http://i3.s1.dpfile.com/pc/28619e4ac5226c9b49c6416a20b8770f(249x249)/thumb.jpg", "name": "Sophie's Cosmic Café", "avg_cost": "0", "review_score": "4", "address": "2095 West 4th Ave", "atmosphere_score": "0", "review_num": "0"}
,{"service_score": "0", "taste_score": "0", "img_url": "http://i1.s1.dpfile.com/pc/7847b295dcfa992d9c5cda6cefff69b0(249x249)/thumb.jpg", "name": "Zero One Sushi", "avg_cost": "0", "review_score": "4", "address": "559 W Pender St", "atmosphere_score": "0", "review_num": "0"}
,{"service_score": "0", "phone": "+1 604 926 3212", "taste_score": "0", "img_url": "http://i1.s1.dpfile.com/pc/785624a5131c583de1ba7127b8b94bff(249x249)/thumb.jpg", "name": "Salmon House on the Hill", "avg_cost": "0", "review_score": "4", "address": "2229 Folkestone Way", "atmosphere_score": "0", "review_num": "0"}
,{"service_score": "0", "taste_score": "0", "img_url": "http://i1.s1.dpfile.com/pc/74ed374c54369a999751eb27d0d9c951(249x249)/thumb.jpg", "name": "Serano Greek Pastry", "avg_cost": "0", "review_score": "4", "address": "3185 W Broadway", "atmosphere_score": "0", "review_num": "0"}
,{"service_score": "0", "taste_score": "0", "img_url": "http://i2.s1.dpfile.com/pc/a793b456ac749c6ab968d8f12b5ef1a0(249x249)/thumb.jpg", "name": "Tera V Burger", "avg_cost": "0", "review_score": "4", "address": "2961 W Broadway", "atmosphere_score": "0", "review_num": "0"}
,{"service_score": "0", "taste_score": "0", "img_url": "http://i2.s1.dpfile.com/pc/e640f215aa1bf8ffe8949a92be6dfe03(249x249)/thumb.jpg", "name": "Flying Pig", "avg_cost": "0", "review_score": "4", "address": "1168 Hamilton St", "atmosphere_score": "0", "review_num": "0"}
,{"service_score": "8.2", "taste_score": "8.2", "img_url": "http://i3.s1.dpfile.com/pc/d54220337e9577129f18b125e912b91b(249x249)/thumb.jpg", "name": "聚湘村", "avg_cost": "0", "tags": "其他", "review_score": "4", "address": "4600 No 3 Road RichmondBC V6X4E8", "atmosphere_score": "8.2", "review_num": "1"}
,{"service_score": "7.3", "taste_score": "7.5", "img_url": "http://i3.s1.dpfile.com/pc/7d920bd73f30b9df1ca1a84e5c5638dc(249x249)/thumb.jpg", "name": "西湖其他酒家", "avg_cost": "0", "tags": "其他", "review_score": "4", "address": "4989 Victoria Dr", "atmosphere_score": "7.3", "review_num": "2"}
,{"service_score": "7.1", "taste_score": "7.1", "img_url": "http://i2.s1.dpfile.com/pc/6430c55b3fcb5c6dc83cc775cd450de8(249x249)/thumb.jpg", "name": "KITA NO DONBURI", "avg_cost": "0", "review_score": "4", "address": "423 Seymour St.Vancouver B.C", "atmosphere_score": "7.1", "review_num": "2"}
,{"service_score": "6.9", "taste_score": "7.1", "img_url": "http://i1.s1.dpfile.com/pc/b6f66e9f897cac22cef204d6381e997a(249x249)/thumb.jpg", "name": "嘉好其他美食之家", "avg_cost": "0", "tags": "中餐", "review_score": "4", "address": "3415 Kingsway, Vancouver, BC, V5R5L3", "atmosphere_score": "6.9", "review_num": "1"}
,{"service_score": "0", "taste_score": "0", "img_url": "http://i1.s1.dpfile.com/pc/547330c7cc68ee14f9298d0b604dc6e2(249x249)/thumb.jpg", "name": "Hakkasan Contemporary Chinese Restaurant", "avg_cost": "0", "review_score": "4", "address": "2188 No 5 Rd, Richmond", "atmosphere_score": "0", "review_num": "0"}
,{"service_score": "6.7", "phone": "1-6825777", "taste_score": "7.2", "img_url": "http://i1.s1.dpfile.com/pc/02560e16db89430f0b2a9f24c7c1dc81(249x249)/thumb.jpg", "name": "Phnom Penh Restaurant", "avg_cost": "0", "tags": "其他", "review_score": "4", "address": "244 Georgia St E, Vancouver, British Columbia, Canada", "atmosphere_score": "6.7", "review_num": "1"}
,{"service_score": "0", "taste_score": "0", "img_url": "http://i1.s1.dpfile.com/pc/6176f54a92cee88a45bd9b4f489bf24f(249x249)/thumb.jpg", "name": "Honey's", "avg_cost": "0", "review_score": "4", "address": "4373 Gallant Ave", "atmosphere_score": "0", "review_num": "0"}
,{"service_score": "0", "taste_score": "0", "img_url": "http://i2.s1.dpfile.com/pc/daa42149bdded6e15d29b42c1946b699(249x249)/thumb.jpg", "name": "Bridges", "avg_cost": "0", "review_score": "4", "address": "1696 Duranleau St", "atmosphere_score": "0", "review_num": "0"}
,{"service_score": "5.9", "phone": "1-6850871", "taste_score": "5.3", "img_url": "http://i1.s1.dpfile.com/pc/5823da83180c210fd8edcab24cc7ee81(249x249)/thumb.jpg", "name": "汉记面家", "avg_cost": "0", "tags": "其他", "review_score": "3", "address": "1339 Robson Street", "atmosphere_score": "5.9", "review_num": "2"}
,{"service_score": "7.0", "phone": "604-207-0386", "taste_score": "7.0", "img_url": "http://i2.s1.dpfile.com/pc/bd93101d027f24a5391b20ef72bfe169(249x249)/thumb.jpg", "name": "大可以", "avg_cost": "0", "tags": "中餐", "review_score": "4", "address": "1060 - 8580 Alexandra Rd Richmond BC V6X4B3", "atmosphere_score": "7.0", "review_num": "1"}
,{"service_score": "7.5", "phone": "0166-25-3401", "taste_score": "7.1", "img_url": "http://i2.s1.dpfile.com/pc/aebeeffc2255e62e567d87931514789d(249x249)/thumb.jpg", "name": "Ramen Santouka", "avg_cost": "0", "review_score": "4", "address": "Sasaki Bldg 1F, 348-3 | 1jo-Dori 8 Chome, Vancouver, British Columbia 070-0031, Canada", "atmosphere_score": "7.5", "review_num": "2"}
,{"service_score": "7.9", "phone": "1-6045688568", "taste_score": "7.9", "img_url": "http://i1.s1.dpfile.com/pc/46593a32365adc785025ca1bab68ea09(249x249)/thumb.jpg", "name": "Waves Coffee House", "avg_cost": "0", "tags": "西餐", "review_score": "4", "address": "492 W.Hastings St.Vancouver,B.C.V6B,1 L1", "atmosphere_score": "7.9", "review_num": "2"}
,{"service_score": "7.2", "phone": "001-604-688-7466", "taste_score": "7.2", "img_url": "http://i3.s1.dpfile.com/pc/75ca03f2339ca7f0ab6e594f3e129dbf(249x249)/thumb.jpg", "name": "Cioppino's Mediterranean Grill", "avg_cost": "0", "review_score": "4", "address": "1133 Hamilton St,Vancouver,BC V6B 5P6加拿大", "atmosphere_score": "7.2", "review_num": "2"}
,{"service_score": "7.1", "phone": "1-604-931-5255", "taste_score": "7.1", "img_url": "http://i3.s1.dpfile.com/pc/31f1217b4c103a75604b4a4e2712231d(249x249)/thumb.jpg", "name": "蝶恋花中西餐厅", "avg_cost": "0", "tags": "西餐", "review_score": "4", "address": "#501B North Road, Coquitlam BC Canada V3J 1N7", "atmosphere_score": "7.1", "review_num": "1"}
,{"service_score": "0", "taste_score": "0", "img_url": "http://i3.s1.dpfile.com/pc/e95d4980f13ef5d0671a4d7b48a32f84(249x249)/thumb.jpg", "name": "Meat & Bread", "avg_cost": "0", "review_score": "4.5", "address": "370 Cambie Street Vancouver, British Columbia | Hastings, Vancouver, British Columbia, Canada", "atmosphere_score": "0", "review_num": "0"}
,{"service_score": "7.5", "phone": "1-6043705540", "taste_score": "8.0", "img_url": "http://i1.s1.dpfile.com/pc/0f8d7bc8466dc3d5d75371d2f9b7408b(249x249)/thumb.jpg", "name": "SURA Korean BBQ", "avg_cost": "0", "tags": "其他", "review_score": "4", "address": "4151 Hazelbridge Way#1830,Richmond", "atmosphere_score": "7.5", "review_num": "2"}
,{"service_score": "0", "phone": "+1 604-685-8080", "taste_score": "0", "img_url": "http://i1.s1.dpfile.com/pc/c084d7d99e08bf2f6bd54788dfc42520(249x249)/thumb.jpg", "name": "Minami Restaurant", "avg_cost": "0", "review_score": "4.5", "address": "1118 Mainland Street, Vancouver, British Columbia V6B 2S2, Canada(Helmcken and Davie)", "atmosphere_score": "0", "review_num": "0"}
,{"service_score": "8.3", "taste_score": "8.3", "img_url": "http://i2.s1.dpfile.com/pc/54a6e8835cb4bc939b0c5ee2743ef317(249x249)/thumb.jpg", "name": "WEST", "avg_cost": "0", "tags": "西餐", "review_score": "4", "address": "2881 Granville St,Vancouver", "atmosphere_score": "8.3", "review_num": "2"}
,{"service_score": "6.7", "taste_score": "6.6", "img_url": "http://i1.s1.dpfile.com/pc/57e642e09ce14c636510fcb9f0e3e4ee(249x249)/thumb.jpg", "name": "Richmond Sushi", "avg_cost": "0", "review_score": "3", "address": "8388 Capstan Way #1488, Richmond, BC  温哥华", "atmosphere_score": "6.7", "review_num": "2"}
,{"service_score": "0", "phone": "+1 604-879-7119", "taste_score": "0", "img_url": "http://i3.s1.dpfile.com/pc/831854dc8b5103e00ae10758d608e48f(249x249)/thumb.jpg", "name": "Chambar", "avg_cost": "0", "review_score": "4.5", "address": "568 Beatty Street, Vancouver, British Columbia V6B 2L3, Canada (Downtown)(Dunsmuir/Pender)", "atmosphere_score": "0", "review_num": "0"}
,{"service_score": "0", "phone": "(604) 568-0303", "taste_score": "0", "img_url": "http://i1.s1.dpfile.com/pc/f809633fbe7aca343ff4fa691133f0d8(249x249)/thumb.jpg", "name": "Chongqing", "avg_cost": "0", "review_score": "4.5", "address": "1260 Robson, Vancouver, British Columbia, Canada", "atmosphere_score": "0", "review_num": "0"}
,{"service_score": "6.9", "phone": "604-683-7671 ", "taste_score": "7.0", "img_url": "http://i3.s1.dpfile.com/pc/536f10470c938c89236f7fb161731b00(249x249)/thumb.jpg", "name": "HY's", "avg_cost": "0", "tags": "西餐", "review_score": "4", "address": "637 Hornby St, Vancouver,", "atmosphere_score": "6.9", "review_num": "1"}
,{"service_score": "6.9", "taste_score": "6.9", "img_url": "http://i3.s1.dpfile.com/pc/3a0433527f791e583516766029bb2234(249x249)/thumb.jpg", "name": "Mink A Chocolate Cafe", "avg_cost": "0", "tags": "西餐", "review_score": "4", "address": "863 West Hastings Street, Vancouver", "atmosphere_score": "6.9", "review_num": "1"}
,{"service_score": "7.0", "taste_score": "7.0", "img_url": "http://i3.s1.dpfile.com/pc/f970b89b8029da054f25d556ccf1f90e(249x249)/thumb.jpg", "name": "Coffee Bar", "avg_cost": "0", "tags": "西餐", "review_score": "4", "address": "10 Water St,Vancouver,BC V6B 1A4加拿大", "atmosphere_score": "7.0", "review_num": "1"}
,{"service_score": "7.1", "phone": "604-932-4540", "taste_score": "7.1", "img_url": "http://i3.s1.dpfile.com/pc/9ba0597ddfc2f27d57f3cae5883f89d2(249x249)/thumb.jpg", "name": "Araxi", "avg_cost": "0", "tags": "其他", "review_score": "4", "address": "4222 Viliage Square, Whistler", "atmosphere_score": "7.1", "review_num": "1"}
,{"service_score": "6.7", "phone": "1-6047371293", "taste_score": "7.5", "img_url": "http://i1.s1.dpfile.com/pc/ec3a9022e8ccff998d9d118d3441a300(249x249)/thumb.jpg", "name": "越宝龍japolo", "avg_cost": "0", "review_score": "3", "address": "2087 W.Broadway,Vancouver", "atmosphere_score": "6.7", "review_num": "1"}
,{"service_score": "7.7", "taste_score": "7.7", "img_url": "http://i2.s1.dpfile.com/pc/a011c1f4c12d4feb14dabe793e9eb5be(249x249)/thumb.jpg", "name": "Hy s Steakhouse ", "avg_cost": "7.7", "tags": "其他", "review_score": "4", "address": "637 Hornby St, Vancouver, British Columbia, V6C 2G3, Canada", "atmosphere_score": "7.7", "review_num": "0"}
,{"service_score": "0", "phone": "(604) 700-4100", "taste_score": "0", "img_url": "http://i1.s1.dpfile.com/pc/63024d79d2b7b8425f1e99e2202bc247(249x249)/thumb.jpg", "name": "BaoQi Eateri", "avg_cost": "0", "review_score": "4.5", "address": "620 Davie Street, Vancouver, British Columbia V6B5B6, Canada", "atmosphere_score": "0", "review_num": "0"}
,{"service_score": "6.8", "phone": "1-7783715033", "taste_score": "6.3", "img_url": "http://i1.s1.dpfile.com/pc/ad722099a05e7f991098159bff6bb08d(249x249)/thumb.jpg", "name": "抄手王", "avg_cost": "6.8", "review_score": "4", "address": "4500 kingsway burnaby", "atmosphere_score": "6.8", "review_num": "0"}
,{"service_score": "7.1", "phone": "604-285-5877", "taste_score": "7.1", "img_url": "http://i1.s1.dpfile.com/pc/5ae161c69187a2f19f7c9d983372583f(249x249)/thumb.jpg", "name": "Toku Japanese Restaurant ", "avg_cost": "0", "tags": "其他", "review_score": "4", "address": "Lansdowne Mall 5300 Mo.3 Road, Richmond", "atmosphere_score": "7.1", "review_num": "1"}
,{"service_score": "7.4", "phone": "604-233-1219", "taste_score": "8.3", "img_url": "http://j3.s2.dpfile.com/s/c/app/shop/i/shop/no-photo-v2.cb489b6dc9f2efe05219ddb61bde98a8.png", "name": "鲍粤轩", "avg_cost": "0", "tags": "其他", "review_score": "4", "address": "8077 Alexandra Rd Richmond BC V6X3A6", "atmosphere_score": "7.4", "review_num": "1"}
,{"service_score": "6.7", "phone": "1-6046827568", "taste_score": "7.4", "img_url": "http://i2.s1.dpfile.com/pc/7e60c463fa8839208b570ef4b04a44ed(249x249)/thumb.jpg", "name": "kintaro ramen", "avg_cost": "0", "review_score": "4", "address": "788 Denman St,Vancouver,BC V6G 2L5", "atmosphere_score": "6.7", "review_num": "1"}
,{"service_score": "7.0", "taste_score": "6.9", "img_url": "http://i3.s1.dpfile.com/pc/25edaf479a56bb97b4a35341a0133925(249x249)/thumb.jpg", "name": "Medina Cafe", "avg_cost": "0", "tags": "西餐", "review_score": "4", "address": "556 Beatty Street, Vancouver", "atmosphere_score": "7.0", "review_num": "1"}
,{"service_score": "7.5", "phone": "(604) 687-2858", "taste_score": "7.5", "img_url": "http://i2.s1.dpfile.com/pc/85cb6d4d508ad4b21c3db3a09e7ee02d(249x249)/thumb.jpg", "name": "Italian Kitchen", "avg_cost": "0", "review_score": "4", "address": "1037 Alberni Street, Vancouver, British Columbia V7V 3H6, Canada(Burrard)", "atmosphere_score": "7.5", "review_num": "1"}
,{"service_score": "7.0", "taste_score": "7.1", "img_url": "http://i3.s1.dpfile.com/pc/79f19e6465f49770f8b1bb9d8bfe2b98(249x249)/thumb.jpg", "name": "Mario's  Coffee  Express", "avg_cost": "0", "tags": "西餐", "review_score": "4", "address": "105-595 Howe Vancouver", "atmosphere_score": "7.0", "review_num": "1"}
,{"service_score": "7.5", "phone": "1-6042337002", "taste_score": "7.5", "img_url": "http://i2.s1.dpfile.com/pc/cd1685558a0c366ddee4fb2665fb3e26(249x249)/thumb.jpg", "name": "Tropika 星马印餐厅", "avg_cost": "0", "tags": "快餐简餐", "review_score": "4", "address": "322 Lansdowne Mall, 5300 No. 3 Road, Richmond", "atmosphere_score": "7.5", "review_num": "1"}
,{"service_score": "6.8", "phone": "604-303-7977 ", "taste_score": "7.1", "img_url": "http://i1.s1.dpfile.com/pc/03a94ce942b746bb2c4ec86570fabb5b(249x249)/thumb.jpg", "name": "梅园", "avg_cost": "0", "tags": "其他", "review_score": "4", "address": "5960 Minoru Blvd., Richmond, ", "atmosphere_score": "6.8", "review_num": "1"}
,{"service_score": "7.1", "taste_score": "7.5", "img_url": "http://i2.s1.dpfile.com/pc/73849810a037029b90b32c2008b1cebb(249x249)/thumb.jpg", "name": "HK BBQ Master", "avg_cost": "0", "tags": "其他", "review_score": "4", "address": "4651 #3 Rd Richmond BC ", "atmosphere_score": "7.1", "review_num": "1"}
,{"service_score": "7.2", "phone": "604-276-8282", "taste_score": "7.2", "img_url": "http://i3.s1.dpfile.com/pc/0237a194163a61529f6ec7387f854616(249x249)/thumb.jpg", "name": "Felicos", "avg_cost": "0", "tags": "西餐", "review_score": "4", "address": "8140 Leslie Rd, Richmond", "atmosphere_score": "7.2", "review_num": "1"}
,{"service_score": "7.1", "phone": "604-273-0888", "taste_score": "7.1", "img_url": "http://i2.s1.dpfile.com/pc/31905dfe6c039a2566467b15143530e2(249x249)/thumb.jpg", "name": "百乐潮州酒家", "avg_cost": "0", "tags": "其他", "review_score": "4", "address": "200 - 7997 Westminster Hwy Richmond BC V6X1A4", "atmosphere_score": "7.1", "review_num": "1"}
,{"service_score": "7.3", "phone": "604-282-5258", "taste_score": "7.3", "img_url": "http://i2.s1.dpfile.com/pc/bd93101d027f24a5391b20ef72bfe169(249x249)/thumb.jpg", "name": "功夫面", "avg_cost": "0", "tags": "其他", "review_score": "4", "address": "1015-8580 Alexandra Road, Richmond", "atmosphere_score": "7.3", "review_num": "1"}
,{"service_score": "7.0", "phone": "604-872-8050", "taste_score": "7.1", "img_url": "http://i1.s1.dpfile.com/pc/012e0332280888f99f24b4a7b29397af(249x249)/thumb.jpg", "name": "Tojo", "avg_cost": "0", "tags": "其他", "review_score": "4", "address": "1133, Broadway, Vancouver", "atmosphere_score": "7.0", "review_num": "1"}
,{"service_score": "7.0", "phone": "604-295-6612 ", "taste_score": "7.0", "img_url": "http://i2.s1.dpfile.com/pc/db0da4a891ee1557def83541b9eb1d63(249x249)/thumb.jpg", "name": "Kitanoya Guu Richmond", "avg_cost": "0", "tags": "日餐", "review_score": "4", "address": "4151 Hazelbridge Way #2790, Richmond", "atmosphere_score": "7.0", "review_num": "1"}
,{"service_score": "7.0", "phone": "1-6045605550", "taste_score": "6.9", "img_url": "http://i3.s1.dpfile.com/pc/0fb5d75e329746eff2ad47e3d45ecf31(249x249)/thumb.jpg", "name": "White spot", "avg_cost": "0", "tags": "快餐简餐", "review_score": "3", "address": "15877 Croydon Drive. Surrey", "atmosphere_score": "7.0", "review_num": "1"}
,{"service_score": "6.8", "taste_score": "7.3", "img_url": "http://i1.s1.dpfile.com/pc/0fe1175ca55d0152e1ca3aeb50eb7f8e(249x249)/thumb.jpg", "name": "功夫面", "avg_cost": "0", "tags": "其他", "review_score": "4", "address": "8580 Alexandra Rd Richmond,BC V6X 4B3", "atmosphere_score": "6.8", "review_num": "1"}
,{"service_score": "0", "phone": "1-6043545858", "taste_score": "0", "img_url": "http://j3.s2.dpfile.com/s/c/app/shop/i/shop/no-photo-v2.cb489b6dc9f2efe05219ddb61bde98a8.png", "name": "家乡小吃 Hometown Food", "avg_cost": "0", "tags": "快餐简餐", "review_score": "0", "address": "2235-8888 odlin cr,richmond,bc", "atmosphere_score": "0", "review_num": "0"}
,{"service_score": "0", "taste_score": "0", "img_url": "http://i2.s1.dpfile.com/pc/b2636764d551024a1919a3df20bb1219(249x249)/thumb.jpg", "name": "HY's Encore", "avg_cost": "0", "review_score": "0", "address": "637 Hornby St Vancouver", "atmosphere_score": "0", "review_num": "0"}
,{"service_score": "0", "phone": "+17786883978", "taste_score": "0", "img_url": "http://i2.s1.dpfile.com/pc/aae0e555dbc0703e743200f67bee3506(249x249)/thumb.jpg", "name": "邦德厨房", "avg_cost": "0", "tags": "快餐简餐", "review_score": "0", "address": "6557 Elgin Ave", "atmosphere_score": "0", "review_num": "0"}
,{"service_score": "0", "phone": "1-604-800-6677", "taste_score": "0", "img_url": "http://i2.s1.dpfile.com/pc/524cc4ca6ccfb7ddf7c73a3d5dfb32c4(249x249)/thumb.jpg", "name": "宁波其他酒家", "avg_cost": "0", "review_score": "0", "address": "1150-4380 NO.3 Place Richomnd B.C", "atmosphere_score": "0", "review_num": "0"}
,{"service_score": "0", "phone": "1-6887338", "taste_score": "0", "img_url": "http://i2.s1.dpfile.com/pc/9aa2592ea8f3ccf430e1eedb683e3101(249x249)/thumb.jpg", "name": "CinCin Ristorante", "avg_cost": "0", "tags": "其他", "review_score": "0", "address": "1154 Robson St, Vancouver, British Columbia V6E 1B2, Canada", "atmosphere_score": "0", "review_num": "0"}
,{"service_score": "0", "taste_score": "0", "img_url": "http://i2.s1.dpfile.com/pc/03b3be266bc98e3212de93ec799ff5b4(249x249)/thumb.jpg", "name": "雪贝尔蛋糕", "avg_cost": "0", "tags": "其他", "review_score": "0", "address": "8419 Granville St.Vancouver", "atmosphere_score": "0", "review_num": "0"}
,{"service_score": "0", "taste_score": "0", "img_url": "http://i3.s1.dpfile.com/pc/5872ae05a7d58125d58b338c1f64be22(249x249)/thumb.jpg", "name": "Old Faithful Shop", "avg_cost": "0", "review_score": "0", "address": "320 WCordova St.Vancouver,BC, V6B 1E8", "atmosphere_score": "0", "review_num": "0"}
,{"service_score": "0", "phone": "604-682-5777", "taste_score": "0", "img_url": "http://i1.s1.dpfile.com/pc/0e248090c52bc62efa1058539c7fa8a7(249x249)/thumb.jpg", "name": "金边小馆", "avg_cost": "0", "tags": "快餐简餐", "review_score": "0", "address": "244 East Georgia Street, Vancouver, BC V6A 1Z7", "atmosphere_score": "0", "review_num": "0"}
,{"service_score": "0", "taste_score": "0", "img_url": "http://j3.s2.dpfile.com/s/c/app/shop/i/shop/no-photo-v2.cb489b6dc9f2efe05219ddb61bde98a8.png", "name": "Earls Kitchen", "avg_cost": "0", "review_score": "0", "address": "1601 west broadway, vancouver bc", "atmosphere_score": "0", "review_num": "0"}
,{"service_score": "0", "phone": "1-6044306808", "taste_score": "0", "img_url": "http://j3.s2.dpfile.com/s/c/app/shop/i/shop/no-photo-v2.cb489b6dc9f2efe05219ddb61bde98a8.png", "name": "Prince Seafood Restaurant", "avg_cost": "0", "tags": "其他", "review_score": "0", "address": "2881 Grandview Highway", "atmosphere_score": "0", "review_num": "0"}
,{"service_score": "0", "phone": "1-6046813330", "taste_score": "0", "img_url": "http://i1.s1.dpfile.com/pc/a97c2f8660cdd7aafc166141ea0a9c90(249x249)/thumb.jpg", "name": "Komi", "avg_cost": "0", "review_score": "0", "address": "100-1100 Melville St. Vancouver, B.C", "atmosphere_score": "0", "review_num": "0"}
,{"service_score": "0", "taste_score": "0", "img_url": "http://j3.s2.dpfile.com/s/c/app/shop/i/shop/no-photo-v2.cb489b6dc9f2efe05219ddb61bde98a8.png", "name": "Steveston Pizza Company", "avg_cost": "0", "tags": "西餐", "review_score": "0", "address": "3400 Moncton Street, Suite 100, Richmond, BC V7E 3A2", "atmosphere_score": "0", "review_num": "0"}
,{"service_score": "0", "taste_score": "0", "img_url": "http://i3.s1.dpfile.com/pc/a3c1c5ca43c102f0365065379bf4b1ef(249x249)/thumb.jpg", "name": "泰麻鲜双人火锅", "avg_cost": "0", "tags": "其他", "review_score": "0", "address": "8391 Alexandra Rd Richmond,BC V6X3W5", "atmosphere_score": "0", "review_num": "0"}
,{"service_score": "0", "taste_score": "0", "img_url": "http://i1.s1.dpfile.com/pc/6f1ded8238d13179da123bf235c4118a(249x249)/thumb.jpg", "name": "东北面馆", "avg_cost": "0", "tags": "其他", "review_score": "0", "address": "108 - 8571Alexandra Rd RichmondBC V6X1C3", "atmosphere_score": "0", "review_num": "0"}
,{"service_score": "0", "taste_score": "0", "img_url": "http://j3.s2.dpfile.com/s/c/app/shop/i/shop/no-photo-v2.cb489b6dc9f2efe05219ddb61bde98a8.png", "name": "Earls", "avg_cost": "0", "review_score": "0", "address": "1601 west broadway, vancouver bc", "atmosphere_score": "0", "review_num": "0"}
,{"service_score": "0", "phone": "1-6381550", "taste_score": "0", "img_url": "http://i3.s1.dpfile.com/pc/5bc482e2e5c84e5383d3717e2b8d4e25(249x249)/thumb.jpg", "name": "Regional Tasting lounge", "avg_cost": "0", "tags": "其他", "review_score": "0", "address": "1130 Mainland street, Vancouver", "atmosphere_score": "0", "review_num": "0"}
,{"service_score": "0", "taste_score": "0", "img_url": "http://i3.s1.dpfile.com/pc/d0721321b19c003ece27682a2498c35d(249x249)/thumb.jpg", "name": "帝皇其他酒家", "avg_cost": "0", "tags": "其他", "review_score": "0", "address": "3502 Kingsway,Vancouver,BC", "atmosphere_score": "0", "review_num": "0"}
,{"service_score": "0", "taste_score": "0", "img_url": "http://i1.s1.dpfile.com/pc/f1e50aee26cca850c671f570ba2437e5(249x249)/thumb.jpg", "name": "Le Marché St. George", "avg_cost": "0", "review_score": "0", "address": "4393 St.George Street Vancouver,BC V5T3S1", "atmosphere_score": "0", "review_num": "0"}
,{"service_score": "0", "taste_score": "0", "img_url": "http://i2.s1.dpfile.com/pc/774c68968d9c1730a0c809b3e8263658(249x249)/thumb.jpg", "name": "Mimi Buloveme", "avg_cost": "0", "review_score": "0", "address": "5556 Cambie St", "atmosphere_score": "0", "review_num": "0"}
,{"service_score": "0", "phone": "1-6857626", "taste_score": "0", "img_url": "http://i3.s1.dpfile.com/pc/062f2d8397b8f24818ef60c07302c2fb(249x249)/thumb.jpg", "name": "Brass Monkey", "avg_cost": "0", "tags": "其他", "review_score": "0", "address": "1072 Denman St.", "atmosphere_score": "0", "review_num": "0"}
,{"service_score": "0", "phone": "1-7305579", "taste_score": "0", "img_url": "http://i2.s1.dpfile.com/pc/d459056af0022244b9b8c20e123e5c47(249x249)/thumb.jpg", "name": "Gastropod餐馆", "avg_cost": "0", "tags": "西餐", "review_score": "0", "address": "1938 W 4th Ave", "atmosphere_score": "0", "review_num": "0"}
,{"service_score": "0", "taste_score": "0", "img_url": "http://i3.s1.dpfile.com/pc/4960e45e7a5b242b63702ced337f2a5d(249x249)/thumb.jpg", "name": "加乐其他酒家", "avg_cost": "0", "tags": "其他", "review_score": "0", "address": "8300 Capstan Way Richmond,BC V6X 4B5(近604-284-5511)", "atmosphere_score": "0", "review_num": "0"}
,{"service_score": "0", "taste_score": "0", "img_url": "http://i3.s1.dpfile.com/pc/ac0ab20a79be78e2d784240ed49cfb92(249x249)/thumb.jpg", "name": "QQ Gelato", "avg_cost": "0", "tags": "其他", "review_score": "0", "address": "1055 Canada Place,#30号(近subway)", "atmosphere_score": "0", "review_num": "0"}
,{"service_score": "0", "taste_score": "0", "img_url": "http://i2.s1.dpfile.com/pc/0fd9b779a2662d73fb7422a169f5a367(249x249)/thumb.jpg", "name": "味太郎", "avg_cost": "0", "tags": "其他", "review_score": "0", "address": "4940 Number 3 Road,Richmond,BC V6X 3A5", "atmosphere_score": "0", "review_num": "0"}
,{"service_score": "0", "taste_score": "0", "img_url": "http://i2.s1.dpfile.com/pc/ef5d413e30c611dc64bb7016acca989e(249x249)/thumb.jpg", "name": "Tastylife Cafe", "avg_cost": "0", "tags": "其他", "review_score": "0", "address": "543 WPender St,Vancouver,BC V6B 1V3", "atmosphere_score": "0", "review_num": "0"}
,{"service_score": "0", "phone": "1-8210828", "taste_score": "0", "img_url": "http://i1.s1.dpfile.com/pc/ebfddf609c0d7664ebc862d386771735(249x249)/thumb.jpg", "name": "鹿鸣春", "avg_cost": "0", "tags": "其他", "review_score": "0", "address": "3700 NO.3 Road, Yaohan Centre (八佰伴中心), Food Court Unit 1100", "atmosphere_score": "0", "review_num": "0"}
,{"service_score": "0", "phone": "1-8211889", "taste_score": "0", "img_url": "http://i1.s1.dpfile.com/pc/66a6d617dc89026a1d012ee9df8cb182(249x249)/thumb.jpg", "name": "Richmond Public Market", "avg_cost": "0", "tags": "其他", "review_score": "0", "address": "Suite 1880-8260 Westminster Hwy, Richmond, BC V6X 1A7加拿大", "atmosphere_score": "0", "review_num": "0"}
,{"service_score": "0", "taste_score": "0", "img_url": "http://i1.s1.dpfile.com/pc/197f062c1ee1de0c8b4a11966f9519af(249x249)/thumb.jpg", "name": "ChocolaTas", "avg_cost": "0", "tags": "甜点", "review_score": "0", "address": "1689 Johnston Street, Vancouver", "atmosphere_score": "0", "review_num": "0"}
,{"service_score": "0", "taste_score": "0", "img_url": "http://i1.s1.dpfile.com/pc/5ae161c69187a2f19f7c9d983372583f(249x249)/thumb.jpg", "name": "Taka s Sushi", "avg_cost": "0", "tags": "其他", "review_score": "0", "address": "15214 Pacific Avenue White Rock, BC V4B 1P7, Canada", "atmosphere_score": "0", "review_num": "0"}
,{"service_score": "0", "taste_score": "0", "img_url": "http://i1.s1.dpfile.com/pc/1d3274fae3fbf5efdff8a120c53c14e9(249x249)/thumb.jpg", "name": "YEW resTaurAnt + Bar", "avg_cost": "0", "tags": "西餐", "review_score": "0", "address": "791 WGeorgia St,Vancouver,BC V6C 2T4加拿大", "atmosphere_score": "0", "review_num": "0"}]
